{"datapath":"us.gov.nrc.us-nuclear-reactors","success":true,"info":{"rows_limit":500,"total_results":100,"total_pages":1,"current_page":1,"calls_remaining":9981,"seconds_remaining":251189},"result":[{"plantname":"Arkansas Nuclear One","unit_number":"Unit 1","nrc_reactor_webpage":"http://www.nrc.gov/info-finder/reactor/ano1.html","docket_number":"5000313","location":"London, AR (6 MI WNW of Russellville, AR)","nrc_region":"4","licensee":"Entergy Operations, Inc.","reactor_containment_type":"PWR-DRYAMB","steam_system_supplier_design":"B&W LLP","architect_engineer":"BECH","contructor":"BECH","construction_permit_issued":"1968-12-06T00:00:00.000Z","operating_license_issued":"1974-05-21T00:00:00.000Z","commercial_operation":"1974-12-19T00:00:00.000Z","renewed_operating_license_issued":"2001-06-20T00:00:00.000Z","operating_license_expires":"2034-05-20T00:00:00.000Z","licensed_mwt":"2568","notes":null,"capacity_factor_percent_2012":"1.02","capacity_factor_percent_2011":"0.87","capacity_factor_percent_2010":"0.9","capacity_factor_percent_2009":"0.99","capacity_factor_percent_2008":"0.83","capacity_factor_percent_2007":"0.94","serialid":1},{"plantname":"Arkansas Nuclear One","unit_number":"Unit 2","nrc_reactor_webpage":"http://www.nrc.gov/info-finder/reactor/ano2.html","docket_number":"5000368","location":"London, AR (6 MI WNW of Russellville, AR)","nrc_region":"4","licensee":"Entergy Operations, Inc.","reactor_containment_type":"PWR-DRYAMB","steam_system_supplier_design":"CE","architect_engineer":"BECH","contructor":"BECH","construction_permit_issued":"1972-12-06T00:00:00.000Z","operating_license_issued":"1978-09-01T00:00:00.000Z","commercial_operation":"1980-03-26T00:00:00.000Z","renewed_operating_license_issued":"2005-06-30T00:00:00.000Z","operating_license_expires":"2038-07-17T00:00:00.000Z","licensed_mwt":"3026","notes":null,"capacity_factor_percent_2012":"0.93","capacity_factor_percent_2011":"0.9","capacity_factor_percent_2010":"0.97","capacity_factor_percent_2009":"0.9","capacity_factor_percent_2008":"0.91","capacity_factor_percent_2007":"0.99","serialid":2},{"plantname":"Beaver Valley Power Station","unit_number":"Unit 1","nrc_reactor_webpage":"http://www.nrc.gov/info-finder/reactor/bv1.html","docket_number":"5000334","location":"Shippingport, PA(17 MI W of McCandless, PA)","nrc_region":"1","licensee":"First Energy Nuclear Operating Co.","reactor_containment_type":"PWR-DRYAMB","steam_system_supplier_design":"WEST 3LP","architect_engineer":"S&W","contructor":"S&W","construction_permit_issued":"1970-06-26T00:00:00.000Z","operating_license_issued":"1976-07-02T00:00:00.000Z","commercial_operation":"1976-10-01T00:00:00.000Z","renewed_operating_license_issued":"2009-11-05T00:00:00.000Z","operating_license_expires":"2036-01-29T00:00:00.000Z","licensed_mwt":"2900","notes":null,"capacity_factor_percent_2012":"0.92","capacity_factor_percent_2011":"1.01","capacity_factor_percent_2010":"0.91","capacity_factor_percent_2009":"0.92","capacity_factor_percent_2008":"1.01","capacity_factor_percent_2007":"0.95","serialid":3},{"plantname":"Beaver Valley Power Station","unit_number":"Unit 2","nrc_reactor_webpage":"http://www.nrc.gov/info-finder/reactor/bv2.html","docket_number":"5000412","location":"Shippingport, PA (17 MI W of McCandless, PA)","nrc_region":"1","licensee":"First Energy Nuclear Operating Co.","reactor_containment_type":"PWR-DRYAMB","steam_system_supplier_design":"WEST 3LP","architect_engineer":"S&W","contructor":"S&W","construction_permit_issued":"1974-05-03T00:00:00.000Z","operating_license_issued":"1987-08-14T00:00:00.000Z","commercial_operation":"1987-11-17T00:00:00.000Z","renewed_operating_license_issued":"2009-11-05T00:00:00.000Z","operating_license_expires":"2047-05-27T00:00:00.000Z","licensed_mwt":"2900","notes":null,"capacity_factor_percent_2012":"0.91","capacity_factor_percent_2011":"1.02","capacity_factor_percent_2010":"0.84","capacity_factor_percent_2009":"0.87","capacity_factor_percent_2008":"1.03","capacity_factor_percent_2007":"0.87","serialid":4},{"plantname":"Braidwood Station","unit_number":"Unit 1","nrc_reactor_webpage":"http://www.nrc.gov/info-finder/reactor/brai1.html","docket_number":"5000456","location":"Braceville, IL (20 MI SSW of Joliet, IL)","nrc_region":"3","licensee":"Exelon Generation Co., LLC","reactor_containment_type":"PWR-DRYAMB","steam_system_supplier_design":"WEST 4LP","architect_engineer":"S&L","contructor":"CWE","construction_permit_issued":"1975-12-31T00:00:00.000Z","operating_license_issued":"1987-07-02T00:00:00.000Z","commercial_operation":"1988-07-29T00:00:00.000Z","renewed_operating_license_issued":null,"operating_license_expires":"2026-10-17T00:00:00.000Z","licensed_mwt":"3586.6","notes":null,"capacity_factor_percent_2012":"0.91","capacity_factor_percent_2011":"1.01","capacity_factor_percent_2010":"0.89","capacity_factor_percent_2009":"0.95","capacity_factor_percent_2008":"1.01","capacity_factor_percent_2007":"0.92","serialid":5},{"plantname":"Braidwood Station","unit_number":"Unit 2","nrc_reactor_webpage":"http://www.nrc.gov/info-finder/reactor/brai2.html","docket_number":"5000457","location":"Braceville, IL (20 MI SSW of Joliet, IL)","nrc_region":"3","licensee":"Exelon Generation Co., LLC","reactor_containment_type":"PWR-DRYAMB","steam_system_supplier_design":"WEST 4LP","architect_engineer":"S&L","contructor":"CWE","construction_permit_issued":"1975-12-31T00:00:00.000Z","operating_license_issued":"1988-05-20T00:00:00.000Z","commercial_operation":"1988-10-17T00:00:00.000Z","renewed_operating_license_issued":null,"operating_license_expires":"2027-12-18T00:00:00.000Z","licensed_mwt":"3586.6","notes":null,"capacity_factor_percent_2012":"0.93","capacity_factor_percent_2011":"0.93","capacity_factor_percent_2010":"0.99","capacity_factor_percent_2009":"0.93","capacity_factor_percent_2008":"0.92","capacity_factor_percent_2007":"1","serialid":6},{"plantname":"Browns Ferry Nuclear Plant","unit_number":"Unit 1","nrc_reactor_webpage":"http://www.nrc.gov/info-finder/reactor/bf1.html","docket_number":"5000259","location":"Limestone County, AL (10 miles south of Athens, AL and 32 MI W of Huntsville, AL)","nrc_region":"2","licensee":"Tenessee Valley Authority","reactor_containment_type":"BWR-MARK 1","steam_system_supplier_design":"GE 4","architect_engineer":"TVA","contructor":"TVA","construction_permit_issued":"1967-05-10T00:00:00.000Z","operating_license_issued":"1973-12-20T00:00:00.000Z","commercial_operation":"1974-08-01T00:00:00.000Z","renewed_operating_license_issued":"2006-05-04T00:00:00.000Z","operating_license_expires":"2033-12-20T00:00:00.000Z","licensed_mwt":"3458","notes":null,"capacity_factor_percent_2012":"0.88","capacity_factor_percent_2011":"0.91","capacity_factor_percent_2010":"0.86","capacity_factor_percent_2009":"0.94","capacity_factor_percent_2008":"0.88","capacity_factor_percent_2007":"0.49","serialid":7},{"plantname":"Browns Ferry Nuclear Plant","unit_number":"Unit 2","nrc_reactor_webpage":"http://www.nrc.gov/info-finder/reactor/bf2.html","docket_number":"5000260","location":"Limestone County, AL (10 miles south of Athens, AL and 32 MI W of Huntsville, AL)","nrc_region":"2","licensee":"Tenessee Valley Authority","reactor_containment_type":"BWR-MARK 1","steam_system_supplier_design":"GE 4","architect_engineer":"TVA","contructor":"TVA","construction_permit_issued":"1967-05-10T00:00:00.000Z","operating_license_issued":"1974-06-28T00:00:00.000Z","commercial_operation":"1975-03-01T00:00:00.000Z","renewed_operating_license_issued":"2006-05-04T00:00:00.000Z","operating_license_expires":"2034-06-28T00:00:00.000Z","licensed_mwt":"3458","notes":null,"capacity_factor_percent_2012":"0.99","capacity_factor_percent_2011":"0.8","capacity_factor_percent_2010":"0.91","capacity_factor_percent_2009":"0.94","capacity_factor_percent_2008":"0.98","capacity_factor_percent_2007":"0.78","serialid":8},{"plantname":"Browns Ferry Nuclear Plant","unit_number":"Unit 3","nrc_reactor_webpage":"http://www.nrc.gov/info-finder/reactor/bf3.html","docket_number":"5000296","location":"Limestone County, AL (10 miles south of Athens, AL and 32 MI W of Huntsville, AL)","nrc_region":"2","licensee":"Tenessee Valley Authority","reactor_containment_type":"BWR-MARK 1","steam_system_supplier_design":"GE 4","architect_engineer":"TVA","contructor":"TVA","construction_permit_issued":"1968-07-31T00:00:00.000Z","operating_license_issued":"1976-07-02T00:00:00.000Z","commercial_operation":"1977-03-01T00:00:00.000Z","renewed_operating_license_issued":"2006-05-04T00:00:00.000Z","operating_license_expires":"2036-07-02T00:00:00.000Z","licensed_mwt":"3458","notes":null,"capacity_factor_percent_2012":"0.83","capacity_factor_percent_2011":"0.87","capacity_factor_percent_2010":"0.81","capacity_factor_percent_2009":"0.95","capacity_factor_percent_2008":"0.81","capacity_factor_percent_2007":"0.93","serialid":9},{"plantname":"Brunswick Steam Electric Plant","unit_number":"Unit 1","nrc_reactor_webpage":"http://www.nrc.gov/info-finder/reactor/bru1.html","docket_number":"5000325","location":"Southport, NC (20 MI S of Wilmington, NC)","nrc_region":"2","licensee":"Carolina Power & Light Co.","reactor_containment_type":"BWR-MARK 1","steam_system_supplier_design":"GE 4","architect_engineer":"UE&C","contructor":"BRRT","construction_permit_issued":"1970-02-07T00:00:00.000Z","operating_license_issued":"1976-09-08T00:00:00.000Z","commercial_operation":"1977-03-18T00:00:00.000Z","renewed_operating_license_issued":"2006-06-26T00:00:00.000Z","operating_license_expires":"2036-09-08T00:00:00.000Z","licensed_mwt":"2923","notes":null,"capacity_factor_percent_2012":"0.77","capacity_factor_percent_2011":"1","capacity_factor_percent_2010":"0.83","capacity_factor_percent_2009":"0.98","capacity_factor_percent_2008":"0.85","capacity_factor_percent_2007":"0.96","serialid":10},{"plantname":"Brunswick Steam Electric Plant","unit_number":"Unit 2","nrc_reactor_webpage":"http://www.nrc.gov/info-finder/reactor/bru2.html","docket_number":"5000324","location":"Southport, NC (20 MI S of Wilmington, NC)","nrc_region":"2","licensee":"Carolina Power & Light Co.","reactor_containment_type":"BWR-MARK 1","steam_system_supplier_design":"GE 4","architect_engineer":"UE&C","contructor":"BRRT","construction_permit_issued":"1970-02-07T00:00:00.000Z","operating_license_issued":"1974-12-27T00:00:00.000Z","commercial_operation":"1975-11-03T00:00:00.000Z","renewed_operating_license_issued":"2006-06-26T00:00:00.000Z","operating_license_expires":"2034-12-27T00:00:00.000Z","licensed_mwt":"2923","notes":null,"capacity_factor_percent_2012":"0.98","capacity_factor_percent_2011":"0.79","capacity_factor_percent_2010":"0.99","capacity_factor_percent_2009":"0.8","capacity_factor_percent_2008":"0.95","capacity_factor_percent_2007":"0.87","serialid":11},{"plantname":"Byron Station","unit_number":"Unit 1","nrc_reactor_webpage":"http://www.nrc.gov/info-finder/reactor/byro1.html","docket_number":"5000454","location":"Byron, Il (17 MI SW of Rockford, IL)","nrc_region":"3","licensee":"Exelon Generation Co., LLC","reactor_containment_type":"PWR-DRYAMB","steam_system_supplier_design":"WEST 4LP","architect_engineer":"S&L","contructor":"CWE","construction_permit_issued":"1975-12-31T00:00:00.000Z","operating_license_issued":"1985-02-14T00:00:00.000Z","commercial_operation":"1985-09-16T00:00:00.000Z","renewed_operating_license_issued":null,"operating_license_expires":"2024-10-31T00:00:00.000Z","licensed_mwt":"3586.6","notes":null,"capacity_factor_percent_2012":"0.88","capacity_factor_percent_2011":"0.88","capacity_factor_percent_2010":"1.01","capacity_factor_percent_2009":"0.94","capacity_factor_percent_2008":"0.95","capacity_factor_percent_2007":"0.98","serialid":12},{"plantname":"Byron Station","unit_number":"Unit 2","nrc_reactor_webpage":"http://www.nrc.gov/info-finder/reactor/byro2.html","docket_number":"5000455","location":"Byron, Il (17 MI SW of Rockford, IL)","nrc_region":"3","licensee":"Exelon Generation Co., LLC","reactor_containment_type":"PWR-DRYAMB","steam_system_supplier_design":"WEST 4LP","architect_engineer":"S&L","contructor":"CWE","construction_permit_issued":"1975-12-31T00:00:00.000Z","operating_license_issued":"1987-01-30T00:00:00.000Z","commercial_operation":"1987-08-02T00:00:00.000Z","renewed_operating_license_issued":null,"operating_license_expires":"2026-11-06T00:00:00.000Z","licensed_mwt":"3586.6","notes":null,"capacity_factor_percent_2012":"0.94","capacity_factor_percent_2011":"0.93","capacity_factor_percent_2010":"0.96","capacity_factor_percent_2009":"1.02","capacity_factor_percent_2008":"0.96","capacity_factor_percent_2007":"0.89","serialid":13},{"plantname":"Callaway Plant","unit_number":null,"nrc_reactor_webpage":"http://www.nrc.gov/info-finder/reactor/call.html","docket_number":"5000483","location":"Fulton, MO (25 MI ENE of Jefferson City, MO)","nrc_region":"4","licensee":"Union Electric Co.","reactor_containment_type":"PWR-DRYAMB","steam_system_supplier_design":"WEST 4LP","architect_engineer":"BECH","contructor":"DANI","construction_permit_issued":"1976-04-16T00:00:00.000Z","operating_license_issued":"1984-10-18T00:00:00.000Z","commercial_operation":"1984-12-19T00:00:00.000Z","renewed_operating_license_issued":null,"operating_license_expires":"2024-10-18T00:00:00.000Z","licensed_mwt":"3565","notes":null,"capacity_factor_percent_2012":"1.03","capacity_factor_percent_2011":"0.9","capacity_factor_percent_2010":"0.86","capacity_factor_percent_2009":"0.98","capacity_factor_percent_2008":"0.9","capacity_factor_percent_2007":"0.9","serialid":14},{"plantname":"Calvert Cliffs Nuclear Power Plant","unit_number":"Unit 1","nrc_reactor_webpage":"http://www.nrc.gov/info-finder/reactor/calv1.html","docket_number":"5000317","location":"Lusby, MD (40 MI S of Annapolis, MD)","nrc_region":"1","licensee":"Calvert Cliffs Nuclear Power Plant Inc.","reactor_containment_type":"PWR-DRYAMB","steam_system_supplier_design":"CE","architect_engineer":"BECH","contructor":"BECH","construction_permit_issued":"1969-07-07T00:00:00.000Z","operating_license_issued":"1974-07-31T00:00:00.000Z","commercial_operation":"1975-05-08T00:00:00.000Z","renewed_operating_license_issued":"2000-03-23T00:00:00.000Z","operating_license_expires":"2034-07-31T00:00:00.000Z","licensed_mwt":"2737","notes":null,"capacity_factor_percent_2012":"0.81","capacity_factor_percent_2011":"1.01","capacity_factor_percent_2010":"0.9","capacity_factor_percent_2009":"0.98","capacity_factor_percent_2008":"0.93","capacity_factor_percent_2007":"0.99","serialid":15},{"plantname":"Calvert Cliffs Nuclear Power Plant","unit_number":"Unit 2","nrc_reactor_webpage":"http://www.nrc.gov/info-finder/reactor/calv2.html","docket_number":"5000318","location":"Lusby, MD (40 MI S of Annapolis, MD)","nrc_region":"1","licensee":"Calvert Cliffs Nuclear Power Plant Inc.","reactor_containment_type":"PWR-DRYAMB","steam_system_supplier_design":"CE","architect_engineer":"BECH","contructor":"BECH","construction_permit_issued":"1969-07-07T00:00:00.000Z","operating_license_issued":"1976-08-13T00:00:00.000Z","commercial_operation":"1977-04-01T00:00:00.000Z","renewed_operating_license_issued":"2000-03-23T00:00:00.000Z","operating_license_expires":"2036-08-13T00:00:00.000Z","licensed_mwt":"2737","notes":null,"capacity_factor_percent_2012":"1.01","capacity_factor_percent_2011":"0.92","capacity_factor_percent_2010":"0.97","capacity_factor_percent_2009":"0.93","capacity_factor_percent_2008":"0.99","capacity_factor_percent_2007":"0.9","serialid":16},{"plantname":"Catawba Nuclear Station","unit_number":"Unit 1","nrc_reactor_webpage":"http://www.nrc.gov/info-finder/reactor/cat1.html","docket_number":"5000413","location":"York, SC (18 MI S of Charlotte,_NC)","nrc_region":"2","licensee":"Duke Energy Carolinas, LLC","reactor_containment_type":"PWR-ICECND","steam_system_supplier_design":"WEST 4LP","architect_engineer":"DUKE","contructor":"DUKE","construction_permit_issued":"1975-08-07T00:00:00.000Z","operating_license_issued":"1985-01-17T00:00:00.000Z","commercial_operation":"1985-06-29T00:00:00.000Z","renewed_operating_license_issued":"2003-12-05T00:00:00.000Z","operating_license_expires":"2043-12-05T00:00:00.000Z","licensed_mwt":"3411","notes":null,"capacity_factor_percent_2012":"0.89","capacity_factor_percent_2011":"0.89","capacity_factor_percent_2010":"1","capacity_factor_percent_2009":"0.91","capacity_factor_percent_2008":"0.89","capacity_factor_percent_2007":"1.02","serialid":17},{"plantname":"Catawba Nuclear Station","unit_number":"Unit 2","nrc_reactor_webpage":"http://www.nrc.gov/info-finder/reactor/cat2.html","docket_number":"5000414","location":"York, SC (18 MI S of Charlotte,_NC)","nrc_region":"2","licensee":"Duke Energy Carolinas, LLC","reactor_containment_type":"PWR-ICECND","steam_system_supplier_design":"WEST 4LP","architect_engineer":"DUKE","contructor":"DUKE","construction_permit_issued":"1975-08-07T00:00:00.000Z","operating_license_issued":"1986-05-15T00:00:00.000Z","commercial_operation":"1986-08-19T00:00:00.000Z","renewed_operating_license_issued":"2003-12-05T00:00:00.000Z","operating_license_expires":"2043-12-05T00:00:00.000Z","licensed_mwt":"3411","notes":null,"capacity_factor_percent_2012":"0.92","capacity_factor_percent_2011":"1.01","capacity_factor_percent_2010":"0.92","capacity_factor_percent_2009":"0.9","capacity_factor_percent_2008":"1.03","capacity_factor_percent_2007":"0.84","serialid":18},{"plantname":"Clinton Power Station","unit_number":"Unit 1","nrc_reactor_webpage":"http://www.nrc.gov/info-finder/reactor/clin.html","docket_number":"5000461","location":"Clinton, IL (23 MI SSE of Bloomington, IL)","nrc_region":"3","licensee":"Exelon Generation Co., LLC","reactor_containment_type":"BWR-MARK 3","steam_system_supplier_design":"GE 6","architect_engineer":"S&L","contructor":"BALD","construction_permit_issued":"1976-02-24T00:00:00.000Z","operating_license_issued":"1987-04-17T00:00:00.000Z","commercial_operation":"1987-11-24T00:00:00.000Z","renewed_operating_license_issued":null,"operating_license_expires":"2026-09-29T00:00:00.000Z","licensed_mwt":"3473","notes":null,"capacity_factor_percent_2012":"1","capacity_factor_percent_2011":"0.93","capacity_factor_percent_2010":"0.92","capacity_factor_percent_2009":"0.97","capacity_factor_percent_2008":"0.99","capacity_factor_percent_2007":"1.01","serialid":19},{"plantname":"Columbia Generating Station","unit_number":"Unit 2","nrc_reactor_webpage":"http://www.nrc.gov/info-finder/reactor/wash2.html","docket_number":"5000397","location":"Richland, WA (20 MI NNE of Pasco, WA)","nrc_region":"4","licensee":"Energy Northwest","reactor_containment_type":"BWR-MARK 2","steam_system_supplier_design":"GE 5","architect_engineer":"B&R","contructor":"BECH","construction_permit_issued":"1973-03-19T00:00:00.000Z","operating_license_issued":"1984-04-13T00:00:00.000Z","commercial_operation":"1984-12-13T00:00:00.000Z","renewed_operating_license_issued":"2012-05-22T00:00:00.000Z","operating_license_expires":"2023-12-20T00:00:00.000Z","licensed_mwt":"3486","notes":null,"capacity_factor_percent_2012":"0.97","capacity_factor_percent_2011":"0.5","capacity_factor_percent_2010":"0.95","capacity_factor_percent_2009":"0.67","capacity_factor_percent_2008":"0.93","capacity_factor_percent_2007":"0.82","serialid":20},{"plantname":"Comanche Peak Steam Electric Station","unit_number":"Unit 1","nrc_reactor_webpage":"http://www.nrc.gov/info-finder/reactor/cp1.html","docket_number":"5000445","location":"Glen Rose, TX (40 MI SW of Fort Worth, TX)","nrc_region":"4","licensee":"Luminant Generation Co., LLC","reactor_containment_type":"PWR-DRYAMB","steam_system_supplier_design":"WEST 4LP","architect_engineer":"G&H","contructor":"BRRT","construction_permit_issued":"1974-12-19T00:00:00.000Z","operating_license_issued":"1990-04-17T00:00:00.000Z","commercial_operation":"1990-08-13T00:00:00.000Z","renewed_operating_license_issued":null,"operating_license_expires":"2030-02-08T00:00:00.000Z","licensed_mwt":"3612","notes":null,"capacity_factor_percent_2012":"0.98","capacity_factor_percent_2011":"0.91","capacity_factor_percent_2010":"0.91","capacity_factor_percent_2009":"1","capacity_factor_percent_2008":"0.96","capacity_factor_percent_2007":"0.85","serialid":21},{"plantname":"Comanche Peak Steam Electric Station","unit_number":"Unit 2","nrc_reactor_webpage":"http://www.nrc.gov/info-finder/reactor/cp2.html","docket_number":"5000446","location":"Glen Rose, TX (40 MI SW of Fort Worth, TX)","nrc_region":"4","licensee":"Luminant Generation Co., LLC","reactor_containment_type":"PWR-DRYAMB","steam_system_supplier_design":"WEST 4LP","architect_engineer":"BECH","contructor":"BRRT","construction_permit_issued":"1974-12-19T00:00:00.000Z","operating_license_issued":"1993-04-06T00:00:00.000Z","commercial_operation":"1993-08-03T00:00:00.000Z","renewed_operating_license_issued":null,"operating_license_expires":"2033-02-02T00:00:00.000Z","licensed_mwt":"3612","notes":null,"capacity_factor_percent_2012":"0.91","capacity_factor_percent_2011":"0.92","capacity_factor_percent_2010":"1.04","capacity_factor_percent_2009":"0.94","capacity_factor_percent_2008":"0.95","capacity_factor_percent_2007":"1.02","serialid":22},{"plantname":"Cooper Nuclear Station","unit_number":null,"nrc_reactor_webpage":"http://www.nrc.gov/info-finder/reactor/cns.html","docket_number":"5000298","location":"Brownville, NE (23 MI S of Nebraska City, NE)","nrc_region":"4","licensee":"Nebraska Public Power District","reactor_containment_type":"BWR-MARK 1","steam_system_supplier_design":"GE 4","architect_engineer":"B&R","contructor":"B&R","construction_permit_issued":"1968-06-04T00:00:00.000Z","operating_license_issued":"1974-01-18T00:00:00.000Z","commercial_operation":"1974-07-01T00:00:00.000Z","renewed_operating_license_issued":"2010-11-29T00:00:00.000Z","operating_license_expires":"2034-01-18T00:00:00.000Z","licensed_mwt":"2419","notes":null,"capacity_factor_percent_2012":"0.87","capacity_factor_percent_2011":"0.86","capacity_factor_percent_2010":"1","capacity_factor_percent_2009":"0.72","capacity_factor_percent_2008":"0.9","capacity_factor_percent_2007":"1","serialid":23},{"plantname":"Davis-Besse Nuclear Power Station","unit_number":"Unit 1","nrc_reactor_webpage":"http://www.nrc.gov/info-finder/reactor/davi.html","docket_number":"5000346","location":"Oak Harbor, OH (21 MI ESE of Toledo, OH)","nrc_region":"3","licensee":"First Energy Nuclear Operating Co.","reactor_containment_type":"PWR-DRYAMB","steam_system_supplier_design":"B&W LLP","architect_engineer":"BECH","contructor":"B&W","construction_permit_issued":"1971-03-24T00:00:00.000Z","operating_license_issued":"1977-04-22T00:00:00.000Z","commercial_operation":"1978-07-31T00:00:00.000Z","renewed_operating_license_issued":null,"operating_license_expires":"2017-04-22T00:00:00.000Z","licensed_mwt":"2817","notes":null,"capacity_factor_percent_2012":"0.91","capacity_factor_percent_2011":"0.81","capacity_factor_percent_2010":"0.66","capacity_factor_percent_2009":"0.99","capacity_factor_percent_2008":"0.97","capacity_factor_percent_2007":"0.99","serialid":24},{"plantname":"Diablo Canyon Nuclear Power Plant","unit_number":"Unit 1","nrc_reactor_webpage":"http://www.nrc.gov/info-finder/reactor/diab1.html","docket_number":"5000275","location":"Avila Beach, CA (12 MI WSW of San Luis Obispo, CA)","nrc_region":"4","licensee":"Pacific Gas & Electric Co.","reactor_containment_type":"PWR-DRYAMB","steam_system_supplier_design":"WEST 4LP","architect_engineer":"PG&E","contructor":"PG&E","construction_permit_issued":"1968-04-23T00:00:00.000Z","operating_license_issued":"1984-11-02T00:00:00.000Z","commercial_operation":"1985-05-07T00:00:00.000Z","renewed_operating_license_issued":null,"operating_license_expires":"2024-11-02T00:00:00.000Z","licensed_mwt":"3411","notes":null,"capacity_factor_percent_2012":"0.84","capacity_factor_percent_2011":"1","capacity_factor_percent_2010":"0.88","capacity_factor_percent_2009":"0.84","capacity_factor_percent_2008":"0.98","capacity_factor_percent_2007":"0.9","serialid":25},{"plantname":"Diablo Canyon Nuclear Power Plant","unit_number":"Unit 2","nrc_reactor_webpage":"http://www.nrc.gov/info-finder/reactor/diab2.html","docket_number":"5000323","location":"Avila Beach, CA (12 MI WSW of San Luis Obispo, CA)","nrc_region":"4","licensee":"Pacific Gas & Electric Co.","reactor_containment_type":"PWR-DRYAMB","steam_system_supplier_design":"WEST 4LP","architect_engineer":"PG&E","contructor":"PG&E","construction_permit_issued":"1970-12-09T00:00:00.000Z","operating_license_issued":"1985-08-26T00:00:00.000Z","commercial_operation":"1986-03-13T00:00:00.000Z","renewed_operating_license_issued":null,"operating_license_expires":"2025-08-26T00:00:00.000Z","licensed_mwt":"3411","notes":null,"capacity_factor_percent_2012":"0.97","capacity_factor_percent_2011":"0.89","capacity_factor_percent_2010":"1","capacity_factor_percent_2009":"0.84","capacity_factor_percent_2008":"0.74","capacity_factor_percent_2007":"0.99","serialid":26},{"plantname":"Donald C. Cook Nuclear Power Plant","unit_number":"Unit 1","nrc_reactor_webpage":"http://www.nrc.gov/info-finder/reactor/cook1.html","docket_number":"5000315","location":"Bridgman, MI (13 M S of Benton Harbor, MI)","nrc_region":"3","licensee":"Indiana Michigan Power Co.","reactor_containment_type":"PWR-ICECND","steam_system_supplier_design":"WEST 4LP","architect_engineer":"AEP","contructor":"AEP","construction_permit_issued":"1969-03-25T00:00:00.000Z","operating_license_issued":"1974-10-25T00:00:00.000Z","commercial_operation":"1975-08-28T00:00:00.000Z","renewed_operating_license_issued":"2005-08-30T00:00:00.000Z","operating_license_expires":"2034-10-25T00:00:00.000Z","licensed_mwt":"3304","notes":null,"capacity_factor_percent_2012":"1.04","capacity_factor_percent_2011":"0.87","capacity_factor_percent_2010":"0.88","capacity_factor_percent_2009":"0.03","capacity_factor_percent_2008":"0.64","capacity_factor_percent_2007":"1.03","serialid":27},{"plantname":"Donald C. Cook Nuclear Power Plant","unit_number":"Unit 2","nrc_reactor_webpage":"http://www.nrc.gov/info-finder/reactor/cook2.html","docket_number":"5000316","location":"Bridgman, MI (13 M S of Benton Harbor, MI)","nrc_region":"3","licensee":"Indiana Michigan Power Co.","reactor_containment_type":"PWR-ICECND","steam_system_supplier_design":"WEST 4LP","architect_engineer":"AEP","contructor":"AEP","construction_permit_issued":"1969-03-25T00:00:00.000Z","operating_license_issued":"1977-12-23T00:00:00.000Z","commercial_operation":"1978-07-01T00:00:00.000Z","renewed_operating_license_issued":"2005-08-30T00:00:00.000Z","operating_license_expires":"2037-12-23T00:00:00.000Z","licensed_mwt":"3468","notes":null,"capacity_factor_percent_2012":"0.91","capacity_factor_percent_2011":"1.04","capacity_factor_percent_2010":"0.84","capacity_factor_percent_2009":"0.87","capacity_factor_percent_2008":"1.01","capacity_factor_percent_2007":"0.86","serialid":28},{"plantname":"Dresden Nuclear Power Station","unit_number":"Unit 2","nrc_reactor_webpage":"http://www.nrc.gov/info-finder/reactor/dres2.html","docket_number":"5000237","location":"Morris, IL (25 M SW of Joliet, IL)","nrc_region":"3","licensee":"Exelon Generation Co., LLC","reactor_containment_type":"BWR-MARK 1","steam_system_supplier_design":"GE 3","architect_engineer":"S&L","contructor":"UE&C","construction_permit_issued":"1966-01-10T00:00:00.000Z","operating_license_issued":"1991-02-20T00:00:00.000Z","commercial_operation":"1970-06-09T00:00:00.000Z","renewed_operating_license_issued":"2004-10-28T00:00:00.000Z","operating_license_expires":"2029-12-22T00:00:00.000Z","licensed_mwt":"2957","notes":"AEC issued a provisional OL on 12/22/1969, allowing commercial operations. The NRC issued a full-term OL on 02/20/1991.","capacity_factor_percent_2012":"1.04","capacity_factor_percent_2011":"0.95","capacity_factor_percent_2010":"1.02","capacity_factor_percent_2009":"0.91","capacity_factor_percent_2008":"0.98","capacity_factor_percent_2007":"0.92","serialid":29},{"plantname":"Dresden Nuclear Power Station","unit_number":"Unit 3","nrc_reactor_webpage":"http://www.nrc.gov/info-finder/reactor/dres3.html","docket_number":"5000249","location":"Morris, IL (25 M SW of Joliet, IL)","nrc_region":"3","licensee":"Exelon Generation Co., LLC","reactor_containment_type":"BWR-MARK 1","steam_system_supplier_design":"GE 3","architect_engineer":"S&L","contructor":"UE&C","construction_permit_issued":"1966-10-14T00:00:00.000Z","operating_license_issued":"1971-01-12T00:00:00.000Z","commercial_operation":"1971-11-16T00:00:00.000Z","renewed_operating_license_issued":"2004-10-28T00:00:00.000Z","operating_license_expires":"2031-01-12T00:00:00.000Z","licensed_mwt":"2957","notes":null,"capacity_factor_percent_2012":"0.91","capacity_factor_percent_2011":"0.99","capacity_factor_percent_2010":"0.9","capacity_factor_percent_2009":"0.97","capacity_factor_percent_2008":"0.93","capacity_factor_percent_2007":"1","serialid":30},{"plantname":"Duane Arnold Energy Center","unit_number":null,"nrc_reactor_webpage":"http://www.nrc.gov/info-finder/reactor/duan.html","docket_number":"5000331","location":"Palo, IA (8 MI NW of Cedar Rapids, IA)","nrc_region":"3","licensee":"FPL Energy Duane Arnold, LLC","reactor_containment_type":"BWR-MARK 1","steam_system_supplier_design":"GE 4","architect_engineer":"BECH","contructor":"BECH","construction_permit_issued":"1970-06-22T00:00:00.000Z","operating_license_issued":"1974-02-22T00:00:00.000Z","commercial_operation":"1975-02-01T00:00:00.000Z","renewed_operating_license_issued":"2010-12-16T00:00:00.000Z","operating_license_expires":"2034-02-21T00:00:00.000Z","licensed_mwt":"1912","notes":null,"capacity_factor_percent_2012":"0.83","capacity_factor_percent_2011":"0.99","capacity_factor_percent_2010":"0.89","capacity_factor_percent_2009":"0.92","capacity_factor_percent_2008":"1.03","capacity_factor_percent_2007":"0.89","serialid":31},{"plantname":"Edwin I. Hatch Nuclear Plant","unit_number":"Unit 1","nrc_reactor_webpage":"http://www.nrc.gov/info-finder/reactor/hat1.html","docket_number":"5000321","location":"Baxley , GA (20 MI S of Vidalia, GA)","nrc_region":"2","licensee":"Southern Nuclear Operating Co.","reactor_containment_type":"BWR-MARK 1","steam_system_supplier_design":"GE 4","architect_engineer":"BECH","contructor":"GPC","construction_permit_issued":"1969-09-30T00:00:00.000Z","operating_license_issued":"1974-10-13T00:00:00.000Z","commercial_operation":"1975-12-31T00:00:00.000Z","renewed_operating_license_issued":"2002-01-15T00:00:00.000Z","operating_license_expires":"2034-08-06T00:00:00.000Z","licensed_mwt":"2804","notes":null,"capacity_factor_percent_2012":"0.89","capacity_factor_percent_2011":"0.98","capacity_factor_percent_2010":"0.85","capacity_factor_percent_2009":"0.94","capacity_factor_percent_2008":"0.84","capacity_factor_percent_2007":"0.98","serialid":32},{"plantname":"Edwin I. Hatch Nuclear Plant","unit_number":"Unit 2","nrc_reactor_webpage":"http://www.nrc.gov/info-finder/reactor/hat2.html","docket_number":"5000366","location":"Baxley , GA (20 MI S of Vidalia, GA)","nrc_region":"2","licensee":"Southern Nuclear Operating Co.","reactor_containment_type":"BWR-MARK 1","steam_system_supplier_design":"GE 4","architect_engineer":"BECH","contructor":"GPC","construction_permit_issued":"1972-12-27T00:00:00.000Z","operating_license_issued":"1978-06-13T00:00:00.000Z","commercial_operation":"1979-09-05T00:00:00.000Z","renewed_operating_license_issued":"2002-01-15T00:00:00.000Z","operating_license_expires":"2038-06-13T00:00:00.000Z","licensed_mwt":"2804","notes":null,"capacity_factor_percent_2012":"0.98","capacity_factor_percent_2011":"0.78","capacity_factor_percent_2010":"0.96","capacity_factor_percent_2009":"0.67","capacity_factor_percent_2008":"0.96","capacity_factor_percent_2007":"0.87","serialid":33},{"plantname":"Fermi","unit_number":"Unit 2","nrc_reactor_webpage":"http://www.nrc.gov/info-finder/reactor/ferm2.html","docket_number":"5000341","location":"Newport, MI (25 MI NE of Toledo, OH)","nrc_region":"3","licensee":"DTE Electric Company","reactor_containment_type":"BWR-MARK 1","steam_system_supplier_design":"GE 4","architect_engineer":"S&L","contructor":"DANI","construction_permit_issued":"1972-09-26T00:00:00.000Z","operating_license_issued":"1985-07-15T00:00:00.000Z","commercial_operation":"1988-01-23T00:00:00.000Z","renewed_operating_license_issued":null,"operating_license_expires":"2025-03-20T00:00:00.000Z","licensed_mwt":"3430","notes":null,"capacity_factor_percent_2012":"0.54","capacity_factor_percent_2011":"0.94","capacity_factor_percent_2010":"0.8","capacity_factor_percent_2009":"0.75","capacity_factor_percent_2008":"0.98","capacity_factor_percent_2007":"0.85","serialid":34},{"plantname":"Fort Calhoun Station","unit_number":"Unit 1","nrc_reactor_webpage":"http://www.nrc.gov/info-finder/reactor/fcs.html","docket_number":"5000285","location":"Fort Calhoun, NE (19 MI N of Omaha, NE)","nrc_region":"4","licensee":"Omaha Public Power District","reactor_containment_type":"PWR-DRYAMB","steam_system_supplier_design":"CE","architect_engineer":"GHDR","contructor":"GHDR","construction_permit_issued":"1968-06-07T00:00:00.000Z","operating_license_issued":"1973-08-09T00:00:00.000Z","commercial_operation":"1973-09-26T00:00:00.000Z","renewed_operating_license_issued":"2003-11-04T00:00:00.000Z","operating_license_expires":"2033-08-09T00:00:00.000Z","licensed_mwt":"1500","notes":null,"capacity_factor_percent_2012":"0","capacity_factor_percent_2011":"0.28","capacity_factor_percent_2010":"1.02","capacity_factor_percent_2009":"1","capacity_factor_percent_2008":"0.83","capacity_factor_percent_2007":"1.04","serialid":35},{"plantname":"Grand Gulf Nuclear Station","unit_number":"Unit 1","nrc_reactor_webpage":"http://www.nrc.gov/info-finder/reactor/gg1.html","docket_number":"5000416","location":"Port Gibson, MS (20 MI S of Vicksburg, MS)","nrc_region":"4","licensee":"Entergy Operations, Inc.","reactor_containment_type":"BWR-MARK 3","steam_system_supplier_design":"GE 6","architect_engineer":"BECH","contructor":"BECH","construction_permit_issued":"1974-09-04T00:00:00.000Z","operating_license_issued":"1984-11-01T00:00:00.000Z","commercial_operation":"1985-07-01T00:00:00.000Z","renewed_operating_license_issued":null,"operating_license_expires":"2024-11-01T00:00:00.000Z","licensed_mwt":"4408","notes":null,"capacity_factor_percent_2012":"0.7","capacity_factor_percent_2011":"0.94","capacity_factor_percent_2010":"0.88","capacity_factor_percent_2009":"1","capacity_factor_percent_2008":"0.86","capacity_factor_percent_2007":"0.84","serialid":36},{"plantname":"H. B. Robinson Steam Electric Plant","unit_number":"Unit 2","nrc_reactor_webpage":"http://www.nrc.gov/info-finder/reactor/rob2.html","docket_number":"5000261","location":"Hartsville, SC (26 MI NW of Florence, SC)","nrc_region":"2","licensee":"Carolina Power & Light Co.,","reactor_containment_type":"PWR-DRYAMB","steam_system_supplier_design":"WEST 3LP","architect_engineer":"EBSO","contructor":"EBSO","construction_permit_issued":"1967-04-13T00:00:00.000Z","operating_license_issued":"1970-07-31T00:00:00.000Z","commercial_operation":"1971-03-07T00:00:00.000Z","renewed_operating_license_issued":"2004-04-19T00:00:00.000Z","operating_license_expires":"2030-07-31T00:00:00.000Z","licensed_mwt":"2339","notes":null,"capacity_factor_percent_2012":"0.85","capacity_factor_percent_2011":"1","capacity_factor_percent_2010":"0.57","capacity_factor_percent_2009":"1.04","capacity_factor_percent_2008":"0.87","capacity_factor_percent_2007":"0.92","serialid":37},{"plantname":"Hope Creek Generating Station","unit_number":"Unit 1","nrc_reactor_webpage":"http://www.nrc.gov/info-finder/reactor/hope.html","docket_number":"5000354","location":"Hancocks Bridge, NJ (18 MI SE of Wilmington, DE)","nrc_region":"1","licensee":"PSEG Nuclear, LLC","reactor_containment_type":"BWR-MARK 1","steam_system_supplier_design":"GE 4","architect_engineer":"BECH","contructor":"BECH","construction_permit_issued":"1974-11-04T00:00:00.000Z","operating_license_issued":"1986-07-25T00:00:00.000Z","commercial_operation":"1986-12-20T00:00:00.000Z","renewed_operating_license_issued":"2011-07-20T00:00:00.000Z","operating_license_expires":"2046-04-11T00:00:00.000Z","licensed_mwt":"3840","notes":null,"capacity_factor_percent_2012":"0.93","capacity_factor_percent_2011":"1.03","capacity_factor_percent_2010":"0.93","capacity_factor_percent_2009":"0.95","capacity_factor_percent_2008":"1.08","capacity_factor_percent_2007":"0.87","serialid":38},{"plantname":"Indian Point Nuclear Generating","unit_number":"Unit 2","nrc_reactor_webpage":"http://www.nrc.gov/info-finder/reactor/ip2.html","docket_number":"5000247","location":"Buchanan, NY (24 MI N of New York, NY)","nrc_region":"1","licensee":"Entergy Nuclear Operations, Inc.","reactor_containment_type":"PWR-DRYAMB","steam_system_supplier_design":"WEST 4LP","architect_engineer":"UE&C","contructor":"WDCO","construction_permit_issued":"1966-10-14T00:00:00.000Z","operating_license_issued":"1973-09-28T00:00:00.000Z","commercial_operation":"1974-08-01T00:00:00.000Z","renewed_operating_license_issued":null,"operating_license_expires":"2013-09-28T00:00:00.000Z","licensed_mwt":"3216","notes":null,"capacity_factor_percent_2012":"0.9","capacity_factor_percent_2011":"0.98","capacity_factor_percent_2010":"0.82","capacity_factor_percent_2009":"0.98","capacity_factor_percent_2008":"0.91","capacity_factor_percent_2007":"0.99","serialid":39},{"plantname":"Indian Point Nuclear Generating","unit_number":"Unit 3","nrc_reactor_webpage":"http://www.nrc.gov/info-finder/reactor/ip3.html","docket_number":"5000286","location":"Buchanan, NY (24 MI N of New York, NY)","nrc_region":"1","licensee":"Entergy Nuclear Operations, Inc.","reactor_containment_type":"PWR-DRYAMB","steam_system_supplier_design":"WEST 4LP","architect_engineer":"UE&C","contructor":"WDCO","construction_permit_issued":"1969-08-13T00:00:00.000Z","operating_license_issued":"1975-12-12T00:00:00.000Z","commercial_operation":"1976-08-30T00:00:00.000Z","renewed_operating_license_issued":null,"operating_license_expires":"2015-12-12T00:00:00.000Z","licensed_mwt":"3216","notes":null,"capacity_factor_percent_2012":"1","capacity_factor_percent_2011":"0.9","capacity_factor_percent_2010":"0.99","capacity_factor_percent_2009":"0.85","capacity_factor_percent_2008":"1.07","capacity_factor_percent_2007":"0.87","serialid":40},{"plantname":"James A. FitzPatrick Nuclear Power Plant","unit_number":null,"nrc_reactor_webpage":"http://www.nrc.gov/info-finder/reactor/fitz.html","docket_number":"5000333","location":"Scriba, NY (6 MI NE of Oswego, NY)","nrc_region":"1","licensee":"Entergy Nuclear FitzPatrick, LLC.","reactor_containment_type":"BWR-MARK 1","steam_system_supplier_design":"GE 4","architect_engineer":"S&W","contructor":"S&W","construction_permit_issued":"1970-05-20T00:00:00.000Z","operating_license_issued":"1974-10-17T00:00:00.000Z","commercial_operation":"1975-07-28T00:00:00.000Z","renewed_operating_license_issued":"2008-09-08T00:00:00.000Z","operating_license_expires":"2034-10-17T00:00:00.000Z","licensed_mwt":"2536","notes":null,"capacity_factor_percent_2012":"0.84","capacity_factor_percent_2011":"0.97","capacity_factor_percent_2010":"0.85","capacity_factor_percent_2009":"0.99","capacity_factor_percent_2008":"0.89","capacity_factor_percent_2007":"0.93","serialid":41},{"plantname":"Joseph M. Farley Nuclear Plant","unit_number":"Unit 1","nrc_reactor_webpage":"http://www.nrc.gov/info-finder/reactor/far1.html","docket_number":"5000348","location":"Columbia, AL (18 MI S of Dothan, AL)","nrc_region":"2","licensee":"Southern Nuclear Operating Co.","reactor_containment_type":"PWR-DRYAMB","steam_system_supplier_design":"WEST 3LP","architect_engineer":"SSI","contructor":"DANI","construction_permit_issued":"1972-08-16T00:00:00.000Z","operating_license_issued":"1977-06-25T00:00:00.000Z","commercial_operation":"1977-12-01T00:00:00.000Z","renewed_operating_license_issued":"2005-05-12T00:00:00.000Z","operating_license_expires":"2037-06-25T00:00:00.000Z","licensed_mwt":"2775","notes":null,"capacity_factor_percent_2012":"0.91","capacity_factor_percent_2011":"1.01","capacity_factor_percent_2010":"0.88","capacity_factor_percent_2009":"0.9","capacity_factor_percent_2008":"0.97","capacity_factor_percent_2007":"0.88","serialid":42},{"plantname":"Joseph M. Farley Nuclear Plant","unit_number":"Unit 2","nrc_reactor_webpage":"http://www.nrc.gov/info-finder/reactor/far2.html","docket_number":"5000364","location":"Columbia, AL (18 MI S of Dothan, AL)","nrc_region":"2","licensee":"Southern Nuclear Operating Co.","reactor_containment_type":"PWR-DRYAMB","steam_system_supplier_design":"WEST 3LP","architect_engineer":"SSI","contructor":"BECH","construction_permit_issued":"1972-08-16T00:00:00.000Z","operating_license_issued":"1981-03-31T00:00:00.000Z","commercial_operation":"1981-07-30T00:00:00.000Z","renewed_operating_license_issued":"2005-05-12T00:00:00.000Z","operating_license_expires":"2041-03-31T00:00:00.000Z","licensed_mwt":"2775","notes":null,"capacity_factor_percent_2012":"1.04","capacity_factor_percent_2011":"0.89","capacity_factor_percent_2010":"0.88","capacity_factor_percent_2009":"0.96","capacity_factor_percent_2008":"0.9","capacity_factor_percent_2007":"0.87","serialid":43},{"plantname":"LaSalle County Station, Unit 1","unit_number":"Unit 1","nrc_reactor_webpage":"http://www.nrc.gov/info-finder/reactor/lasa1.html","docket_number":"5000373","location":"Marseilles, IL (11 MI SE of Ottawa, IL)","nrc_region":"3","licensee":"Exelon Generation Co., LLC","reactor_containment_type":"BWR-MARK 2","steam_system_supplier_design":"GE 5","architect_engineer":"S&L","contructor":"CWE","construction_permit_issued":"1973-09-10T00:00:00.000Z","operating_license_issued":"1982-04-17T00:00:00.000Z","commercial_operation":"1984-01-01T00:00:00.000Z","renewed_operating_license_issued":null,"operating_license_expires":"2022-04-17T00:00:00.000Z","licensed_mwt":"3546","notes":null,"capacity_factor_percent_2012":"0.97","capacity_factor_percent_2011":"1.01","capacity_factor_percent_2010":"0.94","capacity_factor_percent_2009":"0.99","capacity_factor_percent_2008":"1","capacity_factor_percent_2007":"0.99","serialid":44},{"plantname":"LaSalle County Station, Unit 2","unit_number":"Unit 2","nrc_reactor_webpage":"http://www.nrc.gov/info-finder/reactor/lasa2.html","docket_number":"5000374","location":"Marseilles, IL (11 MI SE of Ottawa, IL)","nrc_region":"3","licensee":"Exelon Generation Co., LLC","reactor_containment_type":"BWR-MARK 2","steam_system_supplier_design":"GE 5","architect_engineer":"S&L","contructor":"CWE","construction_permit_issued":"1973-09-10T00:00:00.000Z","operating_license_issued":"1983-12-16T00:00:00.000Z","commercial_operation":"1984-10-19T00:00:00.000Z","renewed_operating_license_issued":null,"operating_license_expires":"2023-12-16T00:00:00.000Z","licensed_mwt":"3546","notes":null,"capacity_factor_percent_2012":"1.03","capacity_factor_percent_2011":"0.96","capacity_factor_percent_2010":"1.01","capacity_factor_percent_2009":"0.93","capacity_factor_percent_2008":"0.94","capacity_factor_percent_2007":"0.95","serialid":45},{"plantname":"Limerick Generating Station","unit_number":"Unit 1","nrc_reactor_webpage":"http://www.nrc.gov/info-finder/reactor/lim1.html","docket_number":"5000352","location":"Limerick, PA (21 MI NW of Philadelphia, PA)","nrc_region":"1","licensee":"Exelon Generation Co., LLC","reactor_containment_type":"BWR-MARK 2","steam_system_supplier_design":"GE 4","architect_engineer":"BECH","contructor":"BECH","construction_permit_issued":"1974-06-19T00:00:00.000Z","operating_license_issued":"1985-08-08T00:00:00.000Z","commercial_operation":"1986-02-01T00:00:00.000Z","renewed_operating_license_issued":null,"operating_license_expires":"2024-10-26T00:00:00.000Z","licensed_mwt":"3515","notes":null,"capacity_factor_percent_2012":"0.85","capacity_factor_percent_2011":"0.96","capacity_factor_percent_2010":"0.91","capacity_factor_percent_2009":"1.01","capacity_factor_percent_2008":"0.95","capacity_factor_percent_2007":"1.01","serialid":46},{"plantname":"Limerick Generating Station","unit_number":"Unit 2","nrc_reactor_webpage":"http://www.nrc.gov/info-finder/reactor/lim2.html","docket_number":"5000353","location":"Limerick, PA (21 MI NW of Philadelphia, PA)","nrc_region":"1","licensee":"Exelon Generation Co., LLC","reactor_containment_type":"BWR-MARK 2","steam_system_supplier_design":"GE 4","architect_engineer":"BECH","contructor":"BECH","construction_permit_issued":"1974-06-19T00:00:00.000Z","operating_license_issued":"1989-08-25T00:00:00.000Z","commercial_operation":"1990-01-08T00:00:00.000Z","renewed_operating_license_issued":null,"operating_license_expires":"2029-06-22T00:00:00.000Z","licensed_mwt":"3515","notes":null,"capacity_factor_percent_2012":"0.95","capacity_factor_percent_2011":"0.9","capacity_factor_percent_2010":"0.99","capacity_factor_percent_2009":"0.94","capacity_factor_percent_2008":"1.01","capacity_factor_percent_2007":"0.91","serialid":47},{"plantname":"McGuire Nuclear Station","unit_number":"Unit 1","nrc_reactor_webpage":"http://www.nrc.gov/info-finder/reactor/mcg1.html","docket_number":"5000369","location":"Huntersville, NC (17 MI N of Charlotte, NC)","nrc_region":"2","licensee":"Duke Energy Carolinas, LLC","reactor_containment_type":"PWR-ICECND","steam_system_supplier_design":"WEST 4LP","architect_engineer":"DUKE","contructor":"DUKE","construction_permit_issued":"1973-02-23T00:00:00.000Z","operating_license_issued":"1981-07-08T00:00:00.000Z","commercial_operation":"1981-12-01T00:00:00.000Z","renewed_operating_license_issued":"2003-12-05T00:00:00.000Z","operating_license_expires":"2041-06-12T00:00:00.000Z","licensed_mwt":"3411","notes":null,"capacity_factor_percent_2012":"1.05","capacity_factor_percent_2011":"0.94","capacity_factor_percent_2010":"0.92","capacity_factor_percent_2009":"1.04","capacity_factor_percent_2008":"0.87","capacity_factor_percent_2007":"0.79","serialid":48},{"plantname":"McGuire Nuclear Station","unit_number":"Unit 2","nrc_reactor_webpage":"http://www.nrc.gov/info-finder/reactor/mcg2.html","docket_number":"5000370","location":"Huntersville, NC (17 MI N of Charlotte, NC)","nrc_region":"2","licensee":"Duke Energy Carolinas, LLC","reactor_containment_type":"PWR-ICECND","steam_system_supplier_design":"WEST 4LP","architect_engineer":"DUKE","contructor":"DUKE","construction_permit_issued":"1973-02-23T00:00:00.000Z","operating_license_issued":"1983-05-27T00:00:00.000Z","commercial_operation":"1984-03-01T00:00:00.000Z","renewed_operating_license_issued":"2003-12-05T00:00:00.000Z","operating_license_expires":"2043-03-03T00:00:00.000Z","licensed_mwt":"3411","notes":null,"capacity_factor_percent_2012":"0.82","capacity_factor_percent_2011":"0.91","capacity_factor_percent_2010":"1.04","capacity_factor_percent_2009":"0.94","capacity_factor_percent_2008":"0.9","capacity_factor_percent_2007":"1.03","serialid":49},{"plantname":"Millstone Power Station","unit_number":"Unit 2","nrc_reactor_webpage":"http://www.nrc.gov/info-finder/reactor/mill1.html","docket_number":"5000336","location":"Waterford. CT (3.2 MI WSW of New London, CT)","nrc_region":"1","licensee":"Dominion Nuclear Conneticut, Inc.","reactor_containment_type":"PWR-DRYAMB","steam_system_supplier_design":"CE","architect_engineer":"BECH","contructor":"BECH","construction_permit_issued":"1970-12-11T00:00:00.000Z","operating_license_issued":"1975-09-26T00:00:00.000Z","commercial_operation":"1975-12-26T00:00:00.000Z","renewed_operating_license_issued":"2005-11-28T00:00:00.000Z","operating_license_expires":"2035-07-31T00:00:00.000Z","licensed_mwt":"2700","notes":null,"capacity_factor_percent_2012":"0.83","capacity_factor_percent_2011":"0.87","capacity_factor_percent_2010":"0.97","capacity_factor_percent_2009":"0.81","capacity_factor_percent_2008":"0.86","capacity_factor_percent_2007":"1","serialid":50},{"plantname":"Millstone Power Station","unit_number":"Unit 3","nrc_reactor_webpage":"http://www.nrc.gov/info-finder/reactor/mill2.html","docket_number":"5000423","location":"Waterford. CT (3.2 MI WSW of New London, CT)","nrc_region":"1","licensee":"Dominion Nuclear Conneticut, Inc.","reactor_containment_type":"PWR-DRYSUB","steam_system_supplier_design":"WEST 4LP","architect_engineer":"S&W","contructor":"S&W","construction_permit_issued":"1974-08-09T00:00:00.000Z","operating_license_issued":"1986-01-31T00:00:00.000Z","commercial_operation":"1986-04-23T00:00:00.000Z","renewed_operating_license_issued":"2005-11-28T00:00:00.000Z","operating_license_expires":"2045-11-25T00:00:00.000Z","licensed_mwt":"3650","notes":null,"capacity_factor_percent_2012":"1","capacity_factor_percent_2011":"0.87","capacity_factor_percent_2010":"0.86","capacity_factor_percent_2009":"1.05","capacity_factor_percent_2008":"0.88","capacity_factor_percent_2007":"0.86","serialid":51},{"plantname":"Monticello Nuclear Generating Plant","unit_number":"Unit 1","nrc_reactor_webpage":"http://www.nrc.gov/info-finder/reactor/mont.html","docket_number":"5000263","location":"Monticello, MN (30 MI NW of Minneapolis, MN)","nrc_region":"3","licensee":"Northern States Power Company - Minnesota","reactor_containment_type":"BWR-MARK 1","steam_system_supplier_design":"GE 3","architect_engineer":"BECH","contructor":"BECH","construction_permit_issued":"1967-06-19T00:00:00.000Z","operating_license_issued":"1981-01-09T00:00:00.000Z","commercial_operation":"1971-06-30T00:00:00.000Z","renewed_operating_license_issued":"2006-11-08T00:00:00.000Z","operating_license_expires":"2030-09-08T00:00:00.000Z","licensed_mwt":"1775","notes":"AEC issued a provisional OL on 09/08/1970, allowing commercial operation. The NRC issued a full-term OL on 01/09/1981.","capacity_factor_percent_2012":"1.01","capacity_factor_percent_2011":"0.69","capacity_factor_percent_2010":"0.94","capacity_factor_percent_2009":"0.83","capacity_factor_percent_2008":"0.97","capacity_factor_percent_2007":"0.84","serialid":52},{"plantname":"Nine Mile Point Nuclear Station","unit_number":"Unit 1","nrc_reactor_webpage":"http://www.nrc.gov/info-finder/reactor/nmp1.html","docket_number":"5000220","location":"Scriba, NY (6 MI NE of Oswego, NY)","nrc_region":"1","licensee":"Nine Mile Point Nuclear Station, LLC","reactor_containment_type":"BWR-MARK 1","steam_system_supplier_design":"GE 2","architect_engineer":"NIAG","contructor":"S&W","construction_permit_issued":"1965-04-12T00:00:00.000Z","operating_license_issued":"1974-12-26T00:00:00.000Z","commercial_operation":"1969-12-01T00:00:00.000Z","renewed_operating_license_issued":"2006-10-31T00:00:00.000Z","operating_license_expires":"2029-08-22T00:00:00.000Z","licensed_mwt":"1850","notes":"AEC issued a provisional OL on 08/22/1969, allowing commercial operation. The NRC issued a full-term OL on 12/26/1974.","capacity_factor_percent_2012":"0.87","capacity_factor_percent_2011":"0.84","capacity_factor_percent_2010":"0.97","capacity_factor_percent_2009":"0.92","capacity_factor_percent_2008":"0.98","capacity_factor_percent_2007":"0.88","serialid":53},{"plantname":"Nine Mile Point Nuclear Station","unit_number":"Unit 2","nrc_reactor_webpage":"http://www.nrc.gov/info-finder/reactor/nmp2.html","docket_number":"5000410","location":"Scriba, NY (6 MI NE of Oswego, NY)","nrc_region":"1","licensee":"Nine Mile Point Nuclear Station, LLC","reactor_containment_type":"BWR-MARK 2","steam_system_supplier_design":"GE 5","architect_engineer":"S&W","contructor":"S&W","construction_permit_issued":"1974-06-24T00:00:00.000Z","operating_license_issued":"1987-07-02T00:00:00.000Z","commercial_operation":"1988-03-11T00:00:00.000Z","renewed_operating_license_issued":"2006-10-31T00:00:00.000Z","operating_license_expires":"2046-10-31T00:00:00.000Z","licensed_mwt":"3988","notes":null,"capacity_factor_percent_2012":"0.83","capacity_factor_percent_2011":"0.95","capacity_factor_percent_2010":"0.89","capacity_factor_percent_2009":"0.99","capacity_factor_percent_2008":"0.9","capacity_factor_percent_2007":"0.92","serialid":54},{"plantname":"North Anna Power Station","unit_number":"Unit 1","nrc_reactor_webpage":"http://www.nrc.gov/info-finder/reactor/na1.html","docket_number":"5000338","location":"Mineral (Louisa County), VA (40 MI NW of Richmond, VA)","nrc_region":"2","licensee":"Virginia Electric & Power Co.","reactor_containment_type":"PWR-DRYSUB","steam_system_supplier_design":"WEST 3LP","architect_engineer":"S&W","contructor":"S&W","construction_permit_issued":"1971-02-19T00:00:00.000Z","operating_license_issued":"1978-04-01T00:00:00.000Z","commercial_operation":"1978-06-06T00:00:00.000Z","renewed_operating_license_issued":"2003-03-20T00:00:00.000Z","operating_license_expires":"2038-04-01T00:00:00.000Z","licensed_mwt":"2940","notes":null,"capacity_factor_percent_2012":"0.89","capacity_factor_percent_2011":"0.78","capacity_factor_percent_2010":"0.86","capacity_factor_percent_2009":"0.92","capacity_factor_percent_2008":"1.01","capacity_factor_percent_2007":"0.89","serialid":55},{"plantname":"North Anna Power Station","unit_number":"Unit 2","nrc_reactor_webpage":"http://www.nrc.gov/info-finder/reactor/na2.html","docket_number":"5000339","location":"Mineral (Louisa County), VA (40 MI NW of Richmond, VA)","nrc_region":"2","licensee":"Virginia Electric & Power Co.","reactor_containment_type":"PWR-DRYSUB","steam_system_supplier_design":"WEST 3LP","architect_engineer":"S&W","contructor":"S&W","construction_permit_issued":"1971-02-19T00:00:00.000Z","operating_license_issued":"1980-08-21T00:00:00.000Z","commercial_operation":"1980-12-14T00:00:00.000Z","renewed_operating_license_issued":"2003-03-20T00:00:00.000Z","operating_license_expires":"2040-08-21T00:00:00.000Z","licensed_mwt":"2940","notes":null,"capacity_factor_percent_2012":"0.99","capacity_factor_percent_2011":"0.76","capacity_factor_percent_2010":"1","capacity_factor_percent_2009":"1","capacity_factor_percent_2008":"0.82","capacity_factor_percent_2007":"0.85","serialid":56},{"plantname":"Oconee Nuclear Station","unit_number":"Unit 1","nrc_reactor_webpage":"http://www.nrc.gov/info-finder/reactor/oco1.html","docket_number":"5000269","location":"Seneca, SC (30 MI W of Greenville, SC)","nrc_region":"2","licensee":"Duke Energy Carolinas, LLC","reactor_containment_type":"PWR-DRYAMB","steam_system_supplier_design":"B&W LLP","architect_engineer":"DBDB","contructor":"DUKE","construction_permit_issued":"1967-11-06T00:00:00.000Z","operating_license_issued":"1973-02-06T00:00:00.000Z","commercial_operation":"1973-07-15T00:00:00.000Z","renewed_operating_license_issued":"2000-05-23T00:00:00.000Z","operating_license_expires":"2033-02-06T00:00:00.000Z","licensed_mwt":"2568","notes":null,"capacity_factor_percent_2012":"0.9","capacity_factor_percent_2011":"0.79","capacity_factor_percent_2010":"1","capacity_factor_percent_2009":"0.85","capacity_factor_percent_2008":"0.84","capacity_factor_percent_2007":"0.99","serialid":57},{"plantname":"Oconee Nuclear Station","unit_number":"Unit 2","nrc_reactor_webpage":"http://www.nrc.gov/info-finder/reactor/oco2.html","docket_number":"5000270","location":"Seneca, SC (30 MI W of Greenville, SC)","nrc_region":"2","licensee":"Duke Energy Carolinas, LLC","reactor_containment_type":"PWR-DRYAMB","steam_system_supplier_design":"B&W LLP","architect_engineer":"DBDB","contructor":"DUKE","construction_permit_issued":"1967-11-06T00:00:00.000Z","operating_license_issued":"1973-10-06T00:00:00.000Z","commercial_operation":"1974-09-09T00:00:00.000Z","renewed_operating_license_issued":"2000-05-23T00:00:00.000Z","operating_license_expires":"2033-10-06T00:00:00.000Z","licensed_mwt":"2568","notes":null,"capacity_factor_percent_2012":"1.02","capacity_factor_percent_2011":"0.93","capacity_factor_percent_2010":"0.91","capacity_factor_percent_2009":"1.03","capacity_factor_percent_2008":"0.86","capacity_factor_percent_2007":"0.91","serialid":58},{"plantname":"Oconee Nuclear Station","unit_number":"Unit 3","nrc_reactor_webpage":"http://www.nrc.gov/info-finder/reactor/oco3.html","docket_number":"5000287","location":"Seneca, SC (30 MI W of Greenville, SC)","nrc_region":"2","licensee":"Duke Energy Carolinas, LLC","reactor_containment_type":"PWR-DRYAMB","steam_system_supplier_design":"B&W LLP","architect_engineer":"DBDB","contructor":"DUKE","construction_permit_issued":"1967-11-06T00:00:00.000Z","operating_license_issued":"1974-07-19T00:00:00.000Z","commercial_operation":"1974-12-16T00:00:00.000Z","renewed_operating_license_issued":"2000-05-23T00:00:00.000Z","operating_license_expires":"2034-07-19T00:00:00.000Z","licensed_mwt":"2568","notes":null,"capacity_factor_percent_2012":"0.86","capacity_factor_percent_2011":"1.03","capacity_factor_percent_2010":"0.91","capacity_factor_percent_2009":"0.94","capacity_factor_percent_2008":"1.02","capacity_factor_percent_2007":"0.87","serialid":59},{"plantname":"Oyster Creek Nuclear Generating Station","unit_number":"Unit 1","nrc_reactor_webpage":"http://www.nrc.gov/info-finder/reactor/oc.html","docket_number":"5000219","location":"Forked River, NJ (9 MI S of Toms River, NJ)","nrc_region":"1","licensee":"Exelon Generation Co., LLC","reactor_containment_type":"BWR-MARK 1","steam_system_supplier_design":"GE 2","architect_engineer":"B&R","contructor":"B&R","construction_permit_issued":"1964-12-15T00:00:00.000Z","operating_license_issued":"1991-07-02T00:00:00.000Z","commercial_operation":"1969-12-01T00:00:00.000Z","renewed_operating_license_issued":"2009-04-08T00:00:00.000Z","operating_license_expires":"2029-04-09T00:00:00.000Z","licensed_mwt":"1930","notes":"AEC issued a provisional OL on 04/09/1969, allowing commercial operation. The NRC issued a full-term OL on 07/02/1991.","capacity_factor_percent_2012":"0.88","capacity_factor_percent_2011":"0.98","capacity_factor_percent_2010":"0.85","capacity_factor_percent_2009":"0.92","capacity_factor_percent_2008":"0.83","capacity_factor_percent_2007":"0.94","serialid":60},{"plantname":"Palisades Nuclear Plant","unit_number":null,"nrc_reactor_webpage":"http://www.nrc.gov/info-finder/reactor/pali.html","docket_number":"5000255","location":"Covert, MI (5 MI S of South Haven, MI)","nrc_region":"3","licensee":"Entergy Nuclear Operations, Inc.","reactor_containment_type":"PWR-DRYAMB","steam_system_supplier_design":"CE","architect_engineer":"BECH","contructor":"BECH","construction_permit_issued":"1967-03-14T00:00:00.000Z","operating_license_issued":"1991-02-21T00:00:00.000Z","commercial_operation":"1971-12-31T00:00:00.000Z","renewed_operating_license_issued":"2007-01-17T00:00:00.000Z","operating_license_expires":"2031-03-24T00:00:00.000Z","licensed_mwt":"2565.4","notes":"AEC issued a provisional OL on 003/24/1971, allowing commercial operation. The NRC issued a full-term OL on 02/21/1991.","capacity_factor_percent_2012":"0.74","capacity_factor_percent_2011":"0.96","capacity_factor_percent_2010":"0.92","capacity_factor_percent_2009":"0.9","capacity_factor_percent_2008":"0.99","capacity_factor_percent_2007":"0.86","serialid":61},{"plantname":"Palo Verde Nuclear Generating Station","unit_number":"Unit 1","nrc_reactor_webpage":"http://www.nrc.gov/info-finder/reactor/palo1.html","docket_number":"5000528","location":"Wintersburg, AZ (50 MI W of Phoenix, AZ)","nrc_region":"4","licensee":"Arizona Public Service Company","reactor_containment_type":"PWR-DRYAMB","steam_system_supplier_design":"CE80-2L","architect_engineer":"BECH","contructor":"BECH","construction_permit_issued":"1976-05-25T00:00:00.000Z","operating_license_issued":"1985-06-01T00:00:00.000Z","commercial_operation":"1986-01-28T00:00:00.000Z","renewed_operating_license_issued":"2011-04-21T00:00:00.000Z","operating_license_expires":"2045-06-01T00:00:00.000Z","licensed_mwt":"3990","notes":null,"capacity_factor_percent_2012":"1","capacity_factor_percent_2011":"0.83","capacity_factor_percent_2010":"0.81","capacity_factor_percent_2009":"1.01","capacity_factor_percent_2008":"0.86","capacity_factor_percent_2007":"0.77","serialid":62},{"plantname":"Palo Verde Nuclear Generating Station","unit_number":"Unit 2","nrc_reactor_webpage":"http://www.nrc.gov/info-finder/reactor/palo2.html","docket_number":"0'5000529","location":"Wintersburg, AZ (50 MI W of Phoenix, AZ)","nrc_region":"4","licensee":"Arizona Public Service Company","reactor_containment_type":"PWR-DRYAMB","steam_system_supplier_design":"CE80-2L","architect_engineer":"BECH","contructor":"BECH","construction_permit_issued":"1976-05-25T00:00:00.000Z","operating_license_issued":"1986-04-24T00:00:00.000Z","commercial_operation":"1986-09-19T00:00:00.000Z","renewed_operating_license_issued":"2011-04-21T00:00:00.000Z","operating_license_expires":"2046-04-24T00:00:00.000Z","licensed_mwt":"3990","notes":null,"capacity_factor_percent_2012":"0.9","capacity_factor_percent_2011":"0.91","capacity_factor_percent_2010":"1.01","capacity_factor_percent_2009":"0.83","capacity_factor_percent_2008":"0.74","capacity_factor_percent_2007":"0.95","serialid":63},{"plantname":"Palo Verde Nuclear Generating Station","unit_number":"Unit 3","nrc_reactor_webpage":"http://www.nrc.gov/info-finder/reactor/palo3.html","docket_number":"5000530","location":"Wintersburg, AZ (50 MI W of Phoenix, AZ)","nrc_region":"4","licensee":"Arizona Public Service Company","reactor_containment_type":"PWR-DRYAMB","steam_system_supplier_design":"COMB CE80-2L","architect_engineer":"BECH","contructor":"BECH","construction_permit_issued":"1976-05-25T00:00:00.000Z","operating_license_issued":"1987-11-25T00:00:00.000Z","commercial_operation":"1988-01-08T00:00:00.000Z","renewed_operating_license_issued":"2011-04-21T00:00:00.000Z","operating_license_expires":"2047-11-25T00:00:00.000Z","licensed_mwt":"3990","notes":null,"capacity_factor_percent_2012":"0.88","capacity_factor_percent_2011":"0.97","capacity_factor_percent_2010":"0.89","capacity_factor_percent_2009":"0.83","capacity_factor_percent_2008":"0.97","capacity_factor_percent_2007":"0.64","serialid":64},{"plantname":"Peach Bottom Atomic Power Station","unit_number":"Unit 2","nrc_reactor_webpage":"http://www.nrc.gov/info-finder/reactor/pb2.html","docket_number":"5000277","location":"Delta, PA (17.9 MI S of Lancaster, PA)","nrc_region":"1","licensee":"Exelon Generation Co., LLC","reactor_containment_type":"BWR-MARK 1","steam_system_supplier_design":"GE 4","architect_engineer":"BECH","contructor":"BECH","construction_permit_issued":"1968-01-31T00:00:00.000Z","operating_license_issued":"1973-10-25T00:00:00.000Z","commercial_operation":"1974-07-05T00:00:00.000Z","renewed_operating_license_issued":"2003-05-07T00:00:00.000Z","operating_license_expires":"2033-08-08T00:00:00.000Z","licensed_mwt":"3514","notes":null,"capacity_factor_percent_2012":"0.88","capacity_factor_percent_2011":"1.01","capacity_factor_percent_2010":"0.92","capacity_factor_percent_2009":"1.02","capacity_factor_percent_2008":"0.89","capacity_factor_percent_2007":"1.01","serialid":65},{"plantname":"Peach Bottom Atomic Power Station","unit_number":"Unit 3","nrc_reactor_webpage":"http://www.nrc.gov/info-finder/reactor/pb3.html","docket_number":"5000278","location":"Delta, PA (17.9 MI S of Lancaster, PA)","nrc_region":"1","licensee":"Exelon Generation Co., LLC","reactor_containment_type":"BWR-MARK 1","steam_system_supplier_design":"GE 4","architect_engineer":"BECH","contructor":"BECH","construction_permit_issued":"1968-01-31T00:00:00.000Z","operating_license_issued":"1974-07-02T00:00:00.000Z","commercial_operation":"1974-12-23T00:00:00.000Z","renewed_operating_license_issued":"2003-05-07T00:00:00.000Z","operating_license_expires":"2034-07-02T00:00:00.000Z","licensed_mwt":"3514","notes":null,"capacity_factor_percent_2012":"1.03","capacity_factor_percent_2011":"0.9","capacity_factor_percent_2010":"1","capacity_factor_percent_2009":"0.89","capacity_factor_percent_2008":"0.99","capacity_factor_percent_2007":"0.93","serialid":66},{"plantname":"Perry Nuclear Power Plant","unit_number":"Unit 1","nrc_reactor_webpage":"http://www.nrc.gov/info-finder/reactor/perr1.html","docket_number":"5000440","location":"Perry, OH (35 MI NE of Cleveland, OH)","nrc_region":"3","licensee":"First Energy Nuclear Operating Co.","reactor_containment_type":"BWR-MARK 3","steam_system_supplier_design":"GE 6","architect_engineer":"GIL","contructor":"KAIS","construction_permit_issued":"1977-05-03T00:00:00.000Z","operating_license_issued":"1986-11-13T00:00:00.000Z","commercial_operation":"1987-11-18T00:00:00.000Z","renewed_operating_license_issued":null,"operating_license_expires":"2026-03-18T00:00:00.000Z","licensed_mwt":"3758","notes":null,"capacity_factor_percent_2012":"0.92","capacity_factor_percent_2011":"0.79","capacity_factor_percent_2010":"0.98","capacity_factor_percent_2009":"0.67","capacity_factor_percent_2008":"0.98","capacity_factor_percent_2007":"0.75","serialid":67},{"plantname":"Pilgrim Nuclear Power Station","unit_number":null,"nrc_reactor_webpage":"http://www.nrc.gov/info-finder/reactor/pilg.html","docket_number":"0'5000293","location":"Plymouth, MA (38 MI SE of Boston, MA)","nrc_region":"1","licensee":"Entergy Nuclear Operations, Inc.","reactor_containment_type":"BWR-MARK 1","steam_system_supplier_design":"GE 3","architect_engineer":"BECH","contructor":"BECH","construction_permit_issued":"1968-08-26T00:00:00.000Z","operating_license_issued":"1972-06-08T00:00:00.000Z","commercial_operation":"1972-12-01T00:00:00.000Z","renewed_operating_license_issued":"2012-05-29T00:00:00.000Z","operating_license_expires":"2032-06-08T00:00:00.000Z","licensed_mwt":"2028","notes":null,"capacity_factor_percent_2012":"0.98","capacity_factor_percent_2011":"0.85","capacity_factor_percent_2010":"0.99","capacity_factor_percent_2009":"0.9","capacity_factor_percent_2008":"0.97","capacity_factor_percent_2007":"0.85","serialid":68},{"plantname":"Point Beach Nuclear Plant","unit_number":"Unit 1","nrc_reactor_webpage":"http://www.nrc.gov/info-finder/reactor/poin1.html","docket_number":"5000266","location":"Two Rivers, WI (13 MI NNW of Manitowoc, WI)","nrc_region":"3","licensee":"NextEra Energy Point Beach, LLC","reactor_containment_type":"PWR-DRYAMB","steam_system_supplier_design":"WEST 2LP","architect_engineer":"BECH","contructor":"BECH","construction_permit_issued":"1967-07-19T00:00:00.000Z","operating_license_issued":"1970-10-05T00:00:00.000Z","commercial_operation":"1970-12-21T00:00:00.000Z","renewed_operating_license_issued":"2005-12-22T00:00:00.000Z","operating_license_expires":"2030-10-05T00:00:00.000Z","licensed_mwt":"1800","notes":null,"capacity_factor_percent_2012":"1","capacity_factor_percent_2011":"0.79","capacity_factor_percent_2010":"0.88","capacity_factor_percent_2009":"0.98","capacity_factor_percent_2008":"0.87","capacity_factor_percent_2007":"0.85","serialid":69},{"plantname":"Point Beach Nuclear Plant","unit_number":"Unit 2","nrc_reactor_webpage":"http://www.nrc.gov/info-finder/reactor/poin2.html","docket_number":"5000301","location":"Two Rivers, WI (13 MI NNW of Manitowoc, WI)","nrc_region":"3","licensee":"NextEra Energy Point Beach, LLC","reactor_containment_type":"PWR-DRYAMB","steam_system_supplier_design":"WEST 2LP","architect_engineer":"BECH","contructor":"BECH","construction_permit_issued":"1968-07-25T00:00:00.000Z","operating_license_issued":"1973-03-08T00:00:00.000Z","commercial_operation":"1972-10-01T00:00:00.000Z","renewed_operating_license_issued":"2005-12-22T00:00:00.000Z","operating_license_expires":"2033-03-08T00:00:00.000Z","licensed_mwt":"1800","notes":"AEC issued a provisional OL on 11/18/1971. The NRC issued a full-term OL on 03/08/1973.","capacity_factor_percent_2012":"0.89","capacity_factor_percent_2011":"0.67","capacity_factor_percent_2010":"0.96","capacity_factor_percent_2009":"0.84","capacity_factor_percent_2008":"0.89","capacity_factor_percent_2007":"0.99","serialid":70},{"plantname":"Prairie Island Nuclear Generating Plant","unit_number":"Unit 1","nrc_reactor_webpage":"http://www.nrc.gov/info-finder/reactor/prai1.html","docket_number":"5000282","location":"Welch, MN (28 MI SE of Minneapolis, MN)","nrc_region":"3","licensee":"Northern States Power Co. Minnesota","reactor_containment_type":"PWR-DRYAMB","steam_system_supplier_design":"WEST 2LP","architect_engineer":"FLUR","contructor":"NSP","construction_permit_issued":"1968-06-25T00:00:00.000Z","operating_license_issued":"1974-04-05T00:00:00.000Z","commercial_operation":"1973-12-16T00:00:00.000Z","renewed_operating_license_issued":"2011-06-27T00:00:00.000Z","operating_license_expires":"2033-08-09T00:00:00.000Z","licensed_mwt":"1677","notes":"AEC issued a provisional OL on 08/09/1973. The NRC issued a full-term OL on 04/05/1974.","capacity_factor_percent_2012":"0.81","capacity_factor_percent_2011":"0.91","capacity_factor_percent_2010":"0.96","capacity_factor_percent_2009":"0.97","capacity_factor_percent_2008":"0.84","capacity_factor_percent_2007":"0.92","serialid":71},{"plantname":"Prairie Island Nuclear Generating Plant","unit_number":"Unit 2","nrc_reactor_webpage":"http://www.nrc.gov/info-finder/reactor/prai2.html","docket_number":"5000306","location":"Welch, MN (28 MI SE of Minneapolis, MN)","nrc_region":"3","licensee":"Northern States Power Co. Minnesota","reactor_containment_type":"PWR-DRYAMB","steam_system_supplier_design":"WEST 2LP","architect_engineer":"FLUR","contructor":"NSP","construction_permit_issued":"1968-06-25T00:00:00.000Z","operating_license_issued":"1974-10-29T00:00:00.000Z","commercial_operation":"1974-12-21T00:00:00.000Z","renewed_operating_license_issued":"2011-06-27T00:00:00.000Z","operating_license_expires":"2034-10-29T00:00:00.000Z","licensed_mwt":"1677","notes":null,"capacity_factor_percent_2012":"0.74","capacity_factor_percent_2011":"0.99","capacity_factor_percent_2010":"0.86","capacity_factor_percent_2009":"0.75","capacity_factor_percent_2008":"0.85","capacity_factor_percent_2007":"0.93","serialid":72},{"plantname":"Quad Cities Nuclear Power Station","unit_number":"Unit 1","nrc_reactor_webpage":"http://www.nrc.gov/info-finder/reactor/quad1.html","docket_number":"5000254","location":"Cordova, IL (20 MI NE of Moline, IL)","nrc_region":"3","licensee":"Exelon Generation Co., LLC","reactor_containment_type":"BWR-MARK 1","steam_system_supplier_design":"GE 3","architect_engineer":"S&L","contructor":"UE&C","construction_permit_issued":"1967-02-15T00:00:00.000Z","operating_license_issued":"1972-12-14T00:00:00.000Z","commercial_operation":"1973-02-18T00:00:00.000Z","renewed_operating_license_issued":"2004-10-28T00:00:00.000Z","operating_license_expires":"2032-12-14T00:00:00.000Z","licensed_mwt":"2957","notes":null,"capacity_factor_percent_2012":"1.02","capacity_factor_percent_2011":"0.92","capacity_factor_percent_2010":"0.99","capacity_factor_percent_2009":"0.82","capacity_factor_percent_2008":"0.96","capacity_factor_percent_2007":"0.92","serialid":73},{"plantname":"Quad Cities Nuclear Power Station","unit_number":"Unit 2","nrc_reactor_webpage":"http://www.nrc.gov/info-finder/reactor/quad2.html","docket_number":"5000265","location":"Cordova, IL (20 MI NE of Moline, IL)","nrc_region":"3","licensee":"Exelon Generation Co., LLC","reactor_containment_type":"BWR-MARK 1","steam_system_supplier_design":"GE 3","architect_engineer":"S&L","contructor":"UE&C","construction_permit_issued":"1967-02-15T00:00:00.000Z","operating_license_issued":"1972-12-14T00:00:00.000Z","commercial_operation":"1973-03-10T00:00:00.000Z","renewed_operating_license_issued":"2004-10-28T00:00:00.000Z","operating_license_expires":"2032-12-14T00:00:00.000Z","licensed_mwt":"2957","notes":null,"capacity_factor_percent_2012":"0.92","capacity_factor_percent_2011":"1.04","capacity_factor_percent_2010":"0.92","capacity_factor_percent_2009":"0.91","capacity_factor_percent_2008":"0.86","capacity_factor_percent_2007":"0.99","serialid":74},{"plantname":"River Bend Station","unit_number":"Unit 1","nrc_reactor_webpage":"http://www.nrc.gov/info-finder/reactor/rbs.html","docket_number":"5000458","location":"St. Francisville, LA (24 MI NNW of Baton Rouge, LA)","nrc_region":"4","licensee":"Entergy Nuclear Operations, Inc.","reactor_containment_type":"BWR-MARK 3","steam_system_supplier_design":"GE 6","architect_engineer":"S&W","contructor":"S&W","construction_permit_issued":"1977-03-25T00:00:00.000Z","operating_license_issued":"1985-11-20T00:00:00.000Z","commercial_operation":"1986-06-16T00:00:00.000Z","renewed_operating_license_issued":null,"operating_license_expires":"2025-08-29T00:00:00.000Z","licensed_mwt":"3091","notes":null,"capacity_factor_percent_2012":"0.91","capacity_factor_percent_2011":"0.9","capacity_factor_percent_2010":"0.98","capacity_factor_percent_2009":"1.13","capacity_factor_percent_2008":"0.82","capacity_factor_percent_2007":"0.85","serialid":75},{"plantname":"R.E. Ginna Nuclear Power Plant","unit_number":null,"nrc_reactor_webpage":"http://www.nrc.gov/info-finder/reactor/ginn.html","docket_number":"5000244","location":"Ontario, NY (20 MI NE of Rochester, NY)","nrc_region":"1","licensee":"R.E. Ginna Nuclear Power Plant, LLC","reactor_containment_type":"PWR-DRYAMB","steam_system_supplier_design":"WEST 2LP","architect_engineer":"GIL","contructor":"BECH","construction_permit_issued":"1966-04-25T00:00:00.000Z","operating_license_issued":"1969-09-19T00:00:00.000Z","commercial_operation":"1970-07-01T00:00:00.000Z","renewed_operating_license_issued":"2004-05-19T00:00:00.000Z","operating_license_expires":"2029-09-18T00:00:00.000Z","licensed_mwt":"1775","notes":null,"capacity_factor_percent_2012":"0.9","capacity_factor_percent_2011":"0.84","capacity_factor_percent_2010":"0.97","capacity_factor_percent_2009":"0.91","capacity_factor_percent_2008":"1.09","capacity_factor_percent_2007":"1.13","serialid":76},{"plantname":"St. Lucie Plant","unit_number":"Unit 1","nrc_reactor_webpage":"http://www.nrc.gov/info-finder/reactor/stl1.html","docket_number":"5000335","location":"Jensen Beach, FL (10 MI SE of Ft. Pierce, FL)","nrc_region":"2","licensee":"Florida Power & Light Co.","reactor_containment_type":"PWR-DRYAMB","steam_system_supplier_design":"CE","architect_engineer":"EBSO","contructor":"EBSO","construction_permit_issued":"1970-07-01T00:00:00.000Z","operating_license_issued":"1976-03-01T00:00:00.000Z","commercial_operation":"1976-12-21T00:00:00.000Z","renewed_operating_license_issued":"2003-10-02T00:00:00.000Z","operating_license_expires":"2036-03-01T00:00:00.000Z","licensed_mwt":"3020","notes":null,"capacity_factor_percent_2012":"0.72","capacity_factor_percent_2011":"0.85","capacity_factor_percent_2010":"0.72","capacity_factor_percent_2009":"1","capacity_factor_percent_2008":"0.91","capacity_factor_percent_2007":"0.85","serialid":77},{"plantname":"St. Lucie Plant","unit_number":"Unit 2","nrc_reactor_webpage":"http://www.nrc.gov/info-finder/reactor/stl2.html","docket_number":"5000389","location":"Jensen Beach, FL (10 MI SE of Ft. Pierce, FL)","nrc_region":"2","licensee":"Florida Power & Light Co.","reactor_containment_type":"PWR-DRYAMB","steam_system_supplier_design":"CE","architect_engineer":"EBSO","contructor":"EBSO","construction_permit_issued":"1977-05-02T00:00:00.000Z","operating_license_issued":"1983-06-10T00:00:00.000Z","commercial_operation":"1983-08-08T00:00:00.000Z","renewed_operating_license_issued":"2003-10-02T00:00:00.000Z","operating_license_expires":"2043-04-06T00:00:00.000Z","licensed_mwt":"3020","notes":null,"capacity_factor_percent_2012":"0.68","capacity_factor_percent_2011":"0.66","capacity_factor_percent_2010":"1","capacity_factor_percent_2009":"0.8","capacity_factor_percent_2008":"0.99","capacity_factor_percent_2007":"0.7","serialid":78},{"plantname":"Salem Nuclear Generating Station","unit_number":"Unit 1","nrc_reactor_webpage":"http://www.nrc.gov/info-finder/reactor/salm1.html","docket_number":"5000272","location":"Hancocks Bridge, NJ (18 MI SE of Wilmington, DE)","nrc_region":"1","licensee":"PSEG Nuclear, LLC","reactor_containment_type":"PWR-DRYAMB","steam_system_supplier_design":"WEST 4LP","architect_engineer":"PUBS","contructor":"UE&C","construction_permit_issued":"1968-09-25T00:00:00.000Z","operating_license_issued":"1976-12-01T00:00:00.000Z","commercial_operation":"1977-06-30T00:00:00.000Z","renewed_operating_license_issued":"2011-06-30T00:00:00.000Z","operating_license_expires":"2036-08-13T00:00:00.000Z","licensed_mwt":"3459","notes":null,"capacity_factor_percent_2012":"0.97","capacity_factor_percent_2011":"0.86","capacity_factor_percent_2010":"0.85","capacity_factor_percent_2009":"0.99","capacity_factor_percent_2008":"0.91","capacity_factor_percent_2007":"0.89","serialid":79},{"plantname":"Salem Nuclear Generating Station","unit_number":"Unit 2","nrc_reactor_webpage":"http://www.nrc.gov/info-finder/reactor/salm2.html","docket_number":"5000311","location":"Hancocks Bridge, NJ (18 MI SE of Wilmington, DE)","nrc_region":"1","licensee":"PSEG Nuclear, LLC","reactor_containment_type":"PWR-DRYAMB","steam_system_supplier_design":"WEST 4LP","architect_engineer":"PUBS","contructor":"UE&C","construction_permit_issued":"1968-09-25T00:00:00.000Z","operating_license_issued":"1981-05-20T00:00:00.000Z","commercial_operation":"1981-10-13T00:00:00.000Z","renewed_operating_license_issued":"2011-06-30T00:00:00.000Z","operating_license_expires":"2040-04-18T00:00:00.000Z","licensed_mwt":"3459","notes":null,"capacity_factor_percent_2012":"0.88","capacity_factor_percent_2011":"0.89","capacity_factor_percent_2010":"0.98","capacity_factor_percent_2009":"0.93","capacity_factor_percent_2008":"0.83","capacity_factor_percent_2007":"0.98","serialid":80},{"plantname":"Seabrook Station","unit_number":"Unit 1","nrc_reactor_webpage":"http://www.nrc.gov/info-finder/reactor/seab1.html","docket_number":"5000443","location":"Seabrook, NH (13 MI S of Portsmouth, NH)","nrc_region":"1","licensee":"NextEra Energy Seabrook, LLC","reactor_containment_type":"PWR-DRYAMB","steam_system_supplier_design":"WEST 4LP","architect_engineer":"UE&C","contructor":"UE&C","construction_permit_issued":"1976-07-07T00:00:00.000Z","operating_license_issued":"1990-03-15T00:00:00.000Z","commercial_operation":"1990-08-19T00:00:00.000Z","renewed_operating_license_issued":null,"operating_license_expires":"2030-03-15T00:00:00.000Z","licensed_mwt":"3648","notes":null,"capacity_factor_percent_2012":"0.75","capacity_factor_percent_2011":"0.77","capacity_factor_percent_2010":"1","capacity_factor_percent_2009":"0.81","capacity_factor_percent_2008":"0.89","capacity_factor_percent_2007":"0.99","serialid":81},{"plantname":"Sequoyah Nuclear Plant","unit_number":"Unit 1","nrc_reactor_webpage":"http://www.nrc.gov/info-finder/reactor/seq1.html","docket_number":"5000327","location":"Soddy-Daisy, TN (16 MI NE of Chattanooga, TN)","nrc_region":"2","licensee":"Tenessee Valley Authority","reactor_containment_type":"PWR-ICECND","steam_system_supplier_design":"WEST 4LP","architect_engineer":"TVA","contructor":"TVA","construction_permit_issued":"1970-05-27T00:00:00.000Z","operating_license_issued":"1980-09-17T00:00:00.000Z","commercial_operation":"1981-07-01T00:00:00.000Z","renewed_operating_license_issued":null,"operating_license_expires":"2020-09-17T00:00:00.000Z","licensed_mwt":"3455","notes":null,"capacity_factor_percent_2012":"0.89","capacity_factor_percent_2011":"0.98","capacity_factor_percent_2010":"0.84","capacity_factor_percent_2009":"0.89","capacity_factor_percent_2008":"1.01","capacity_factor_percent_2007":"0.87","serialid":82},{"plantname":"Sequoyah Nuclear Plant","unit_number":"Unit 2","nrc_reactor_webpage":"http://www.nrc.gov/info-finder/reactor/seq2.html","docket_number":"5000328","location":"Soddy-Daisy, TN (16 MI NE of Chattanooga, TN)","nrc_region":"2","licensee":"Tenessee Valley Authority","reactor_containment_type":"PWR-ICECND","steam_system_supplier_design":"WEST 4LP","architect_engineer":"TVA","contructor":"TVA","construction_permit_issued":"1970-05-27T00:00:00.000Z","operating_license_issued":"1981-09-15T00:00:00.000Z","commercial_operation":"1982-06-01T00:00:00.000Z","renewed_operating_license_issued":null,"operating_license_expires":"2021-09-15T00:00:00.000Z","licensed_mwt":"3455","notes":null,"capacity_factor_percent_2012":"0.77","capacity_factor_percent_2011":"0.89","capacity_factor_percent_2010":"0.97","capacity_factor_percent_2009":"0.89","capacity_factor_percent_2008":"0.89","capacity_factor_percent_2007":"1","serialid":83},{"plantname":"Shearon Harris Nuclear Power Plant","unit_number":"Unit 1","nrc_reactor_webpage":"http://www.nrc.gov/info-finder/reactor/har1.html","docket_number":"5000400","location":"New Hill, NC (20 MI SW of Raleigh, NC)","nrc_region":"2","licensee":"Carolina Power & Light Co.","reactor_containment_type":"PWR-DRYAMB","steam_system_supplier_design":"WEST 3LP","architect_engineer":"EBSO","contructor":"DANI","construction_permit_issued":"1978-01-27T00:00:00.000Z","operating_license_issued":"1986-10-24T00:00:00.000Z","commercial_operation":"1987-05-02T00:00:00.000Z","renewed_operating_license_issued":"2008-12-17T00:00:00.000Z","operating_license_expires":"2046-10-24T00:00:00.000Z","licensed_mwt":"2900","notes":null,"capacity_factor_percent_2012":"0.9","capacity_factor_percent_2011":"1.03","capacity_factor_percent_2010":"0.9","capacity_factor_percent_2009":"0.94","capacity_factor_percent_2008":"0.99","capacity_factor_percent_2007":"0.94","serialid":84},{"plantname":"South Texas Project","unit_number":"Unit 1","nrc_reactor_webpage":"http://www.nrc.gov/info-finder/reactor/stp1.html","docket_number":"5000498","location":"Bay City, TX (90 MI SW of Houston, TX)","nrc_region":"4","licensee":"STP Nuclear Operating Co.","reactor_containment_type":"PWR-DRYAMB","steam_system_supplier_design":"WEST 4LP","architect_engineer":"BECH","contructor":"EBSO","construction_permit_issued":"1975-12-22T00:00:00.000Z","operating_license_issued":"1988-03-22T00:00:00.000Z","commercial_operation":"1988-08-25T00:00:00.000Z","renewed_operating_license_issued":null,"operating_license_expires":"2027-08-20T00:00:00.000Z","licensed_mwt":"3853","notes":null,"capacity_factor_percent_2012":"0.93","capacity_factor_percent_2011":"0.94","capacity_factor_percent_2010":"1.01","capacity_factor_percent_2009":"0.9","capacity_factor_percent_2008":"0.95","capacity_factor_percent_2007":"1.05","serialid":85},{"plantname":"South Texas Project","unit_number":"Unit 2","nrc_reactor_webpage":"http://www.nrc.gov/info-finder/reactor/stp2.html","docket_number":"5000499","location":"Bay City, TX (90 MI SW of Houston, TX)","nrc_region":"4","licensee":"STP Nuclear Operating Co.","reactor_containment_type":"PWR-DRYAMB","steam_system_supplier_design":"WEST 4LP","architect_engineer":"BECH","contructor":"EBSO","construction_permit_issued":"1975-12-22T00:00:00.000Z","operating_license_issued":"1989-03-28T00:00:00.000Z","commercial_operation":"1989-06-19T00:00:00.000Z","renewed_operating_license_issued":null,"operating_license_expires":"2028-12-15T00:00:00.000Z","licensed_mwt":"3853","notes":null,"capacity_factor_percent_2012":"0.72","capacity_factor_percent_2011":"0.88","capacity_factor_percent_2010":"0.88","capacity_factor_percent_2009":"1.01","capacity_factor_percent_2008":"0.95","capacity_factor_percent_2007":"0.93","serialid":86},{"plantname":"Surry Nuclear Power Station","unit_number":"Unit 1","nrc_reactor_webpage":"http://www.nrc.gov/info-finder/reactor/sur1.html","docket_number":"5000280","location":"Surry, VA (17 MI NW of Newport News, VA)","nrc_region":"2","licensee":"Virginia Electric & Power Co.","reactor_containment_type":"PWR-DRYSUB","steam_system_supplier_design":"WEST 3LP","architect_engineer":"S&W","contructor":"S&W","construction_permit_issued":"1968-06-25T00:00:00.000Z","operating_license_issued":"1972-05-25T00:00:00.000Z","commercial_operation":"1972-12-22T00:00:00.000Z","renewed_operating_license_issued":"2003-03-20T00:00:00.000Z","operating_license_expires":"2032-05-25T00:00:00.000Z","licensed_mwt":"2857","notes":null,"capacity_factor_percent_2012":"0.92","capacity_factor_percent_2011":"1.01","capacity_factor_percent_2010":"0.89","capacity_factor_percent_2009":"0.94","capacity_factor_percent_2008":"0.98","capacity_factor_percent_2007":"0.89","serialid":87},{"plantname":"Surry Nuclear Power Station","unit_number":"Unit 2","nrc_reactor_webpage":"http://www.nrc.gov/info-finder/reactor/sur2.html","docket_number":"5000281","location":"Surry, VA (17 MI NW of Newport News, VA)","nrc_region":"2","licensee":"Virginia Electric & Power Co.","reactor_containment_type":"PWR-DRYSUB","steam_system_supplier_design":"WEST 3LP","architect_engineer":"S&W","contructor":"S&W","construction_permit_issued":"1968-06-25T00:00:00.000Z","operating_license_issued":"1973-01-29T00:00:00.000Z","commercial_operation":"1973-05-01T00:00:00.000Z","renewed_operating_license_issued":"2003-03-20T00:00:00.000Z","operating_license_expires":"2033-01-29T00:00:00.000Z","licensed_mwt":"2857","notes":null,"capacity_factor_percent_2012":"0.91","capacity_factor_percent_2011":"0.76","capacity_factor_percent_2010":"1","capacity_factor_percent_2009":"0.92","capacity_factor_percent_2008":"0.94","capacity_factor_percent_2007":"1.01","serialid":88},{"plantname":"Susquehanna Steam Electric Station","unit_number":"Unit 1","nrc_reactor_webpage":"http://www.nrc.gov/info-finder/reactor/susq1.html","docket_number":"5000388","location":"Salem Township, Luzerne Co., PA (70 MI NE of Harrisburg, PA)","nrc_region":"1","licensee":"PPL Susquehanna, LLC","reactor_containment_type":"BWR-MARK 2","steam_system_supplier_design":"GE 4","architect_engineer":"BECH","contructor":"BECH","construction_permit_issued":"1973-11-03T00:00:00.000Z","operating_license_issued":"1982-07-17T00:00:00.000Z","commercial_operation":"1983-06-08T00:00:00.000Z","renewed_operating_license_issued":"2009-11-24T00:00:00.000Z","operating_license_expires":"2042-07-17T00:00:00.000Z","licensed_mwt":"3952","notes":null,"capacity_factor_percent_2012":"0.7","capacity_factor_percent_2011":"0.86","capacity_factor_percent_2010":"0.8","capacity_factor_percent_2009":"1.01","capacity_factor_percent_2008":"0.89","capacity_factor_percent_2007":"0.95","serialid":89},{"plantname":"Susquehanna Steam Electric Station","unit_number":"Unit 2","nrc_reactor_webpage":"http://www.nrc.gov/info-finder/reactor/susq2.html","docket_number":"5000387","location":"Salem Township, Luzerne Co., PA (70 MI NE of Harrisburg, PA)","nrc_region":"1","licensee":"PPL Susquehanna, LLC","reactor_containment_type":"BWR-MARK 2","steam_system_supplier_design":"GE 4","architect_engineer":"BECH","contructor":"BECH","construction_permit_issued":"1973-11-03T00:00:00.000Z","operating_license_issued":"1984-03-23T00:00:00.000Z","commercial_operation":"1985-02-12T00:00:00.000Z","renewed_operating_license_issued":"2009-11-24T00:00:00.000Z","operating_license_expires":"2044-03-23T00:00:00.000Z","licensed_mwt":"3952","notes":null,"capacity_factor_percent_2012":"0.83","capacity_factor_percent_2011":"0.72","capacity_factor_percent_2010":"0.96","capacity_factor_percent_2009":"0.9","capacity_factor_percent_2008":"1","capacity_factor_percent_2007":"0.88","serialid":90},{"plantname":"Three Mile Island Nuclear Station","unit_number":"Unit 1","nrc_reactor_webpage":"http://www.nrc.gov/info-finder/reactor/tmi1.html","docket_number":"5000289","location":"Middletown, PA (10 MI SE of Harrisburg, PA)","nrc_region":"1","licensee":"Exelon Generation Co., LLC","reactor_containment_type":"PWR-DRYAMB","steam_system_supplier_design":"B&W LLP","architect_engineer":"GIL","contructor":"UE&C","construction_permit_issued":"1968-05-18T00:00:00.000Z","operating_license_issued":"1974-04-19T00:00:00.000Z","commercial_operation":"1974-09-02T00:00:00.000Z","renewed_operating_license_issued":"2009-10-22T00:00:00.000Z","operating_license_expires":"2034-04-19T00:00:00.000Z","licensed_mwt":"2568","notes":null,"capacity_factor_percent_2012":"1","capacity_factor_percent_2011":"0.92","capacity_factor_percent_2010":"0.94","capacity_factor_percent_2009":"0.86","capacity_factor_percent_2008":"1.07","capacity_factor_percent_2007":"0.97","serialid":91},{"plantname":"Turkey Point Nuclear Generating","unit_number":"Unit 3","nrc_reactor_webpage":"http://www.nrc.gov/info-finder/reactor/tp3.html","docket_number":"5000250","location":"Homestead, FL (20 MI S of Miami, FL)","nrc_region":"2","licensee":"Florida Power & Light Co.","reactor_containment_type":"PWR-DRYAMB","steam_system_supplier_design":"WEST 3LP","architect_engineer":"BECH","contructor":"BECH","construction_permit_issued":"1967-04-27T00:00:00.000Z","operating_license_issued":"1972-07-19T00:00:00.000Z","commercial_operation":"1972-12-14T00:00:00.000Z","renewed_operating_license_issued":"2002-06-06T00:00:00.000Z","operating_license_expires":"2032-07-19T00:00:00.000Z","licensed_mwt":"2644","notes":null,"capacity_factor_percent_2012":"0.4","capacity_factor_percent_2011":"0.96","capacity_factor_percent_2010":"0.88","capacity_factor_percent_2009":"0.86","capacity_factor_percent_2008":"1.01","capacity_factor_percent_2007":"0.97","serialid":92},{"plantname":"Turkey Point Nuclear Generating, Unit 4","unit_number":"Unit 4","nrc_reactor_webpage":"http://www.nrc.gov/info-finder/reactor/tp4.html","docket_number":"5000251","location":"Homestead, FL (20 MI S of Miami, FL)","nrc_region":"2","licensee":"Florida Power & Light Co.","reactor_containment_type":"PWR-DRYAMB","steam_system_supplier_design":"WEST 3LP","architect_engineer":"BECH","contructor":"BECH","construction_permit_issued":"1967-04-27T00:00:00.000Z","operating_license_issued":"1973-04-10T00:00:00.000Z","commercial_operation":"1973-09-07T00:00:00.000Z","renewed_operating_license_issued":"2002-06-06T00:00:00.000Z","operating_license_expires":"2033-04-10T00:00:00.000Z","licensed_mwt":"2644","notes":null,"capacity_factor_percent_2012":"0.85","capacity_factor_percent_2011":"0.84","capacity_factor_percent_2010":"0.98","capacity_factor_percent_2009":"0.99","capacity_factor_percent_2008":"0.89","capacity_factor_percent_2007":"0.86","serialid":93},{"plantname":"Vermont Yankee Nuclear Power Plant","unit_number":"Unit 1","nrc_reactor_webpage":"http://www.nrc.gov/info-finder/reactor/vy.html","docket_number":"5000271","location":"Vernon, VT (5 MI S of Brattleboro, VT)","nrc_region":"1","licensee":"Entergy Nuclear Operations, Inc.","reactor_containment_type":"BWR-MARK 1","steam_system_supplier_design":"GE 4","architect_engineer":"EBSO","contructor":"EBSO","construction_permit_issued":"1967-12-11T00:00:00.000Z","operating_license_issued":"1972-03-21T00:00:00.000Z","commercial_operation":"1972-11-30T00:00:00.000Z","renewed_operating_license_issued":"2011-03-21T00:00:00.000Z","operating_license_expires":"2032-03-21T00:00:00.000Z","licensed_mwt":"1912","notes":null,"capacity_factor_percent_2012":"0.92","capacity_factor_percent_2011":"0.9","capacity_factor_percent_2010":"0.88","capacity_factor_percent_2009":"0.99","capacity_factor_percent_2008":"0.89","capacity_factor_percent_2007":"0.87","serialid":94},{"plantname":"Virgil C. Summer Nuclear Station","unit_number":"Unit 1","nrc_reactor_webpage":"http://www.nrc.gov/info-finder/reactor/sum.html","docket_number":"5000395","location":"Jenkinsville, SC (26 MI NW of Columbia, SC)","nrc_region":"2","licensee":"South Carolina Electric & Gas Co.","reactor_containment_type":"PWR-DRYAMB","steam_system_supplier_design":"WEST 3LP","architect_engineer":"GIL","contructor":"DANI","construction_permit_issued":"1973-03-21T00:00:00.000Z","operating_license_issued":"1982-11-12T00:00:00.000Z","commercial_operation":"1984-01-01T00:00:00.000Z","renewed_operating_license_issued":"2004-04-23T00:00:00.000Z","operating_license_expires":"2042-08-06T00:00:00.000Z","licensed_mwt":"2900","notes":null,"capacity_factor_percent_2012":"0.86","capacity_factor_percent_2011":"0.88","capacity_factor_percent_2010":"1","capacity_factor_percent_2009":"0.81","capacity_factor_percent_2008":"0.87","capacity_factor_percent_2007":"0.85","serialid":95},{"plantname":"Vogtle Electric Generating Plant","unit_number":"Unit 1","nrc_reactor_webpage":"http://www.nrc.gov/info-finder/reactor/vog1.html","docket_number":"5000424","location":"Waynesboro, GA (26 MI SE of Augusta, GA)","nrc_region":"2","licensee":"Southern Nuclear Operating Co.","reactor_containment_type":"PWR-DRYAMB","steam_system_supplier_design":"WEST 4LP","architect_engineer":"SBEC","contructor":"GPC","construction_permit_issued":"1974-06-28T00:00:00.000Z","operating_license_issued":"1987-03-16T00:00:00.000Z","commercial_operation":"1987-06-01T00:00:00.000Z","renewed_operating_license_issued":"2009-06-03T00:00:00.000Z","operating_license_expires":"2047-01-16T00:00:00.000Z","licensed_mwt":"3625.6","notes":null,"capacity_factor_percent_2012":"0.91","capacity_factor_percent_2011":"0.92","capacity_factor_percent_2010":"1.02","capacity_factor_percent_2009":"0.91","capacity_factor_percent_2008":"0.93","capacity_factor_percent_2007":"0.99","serialid":96},{"plantname":"Vogtle Electric Generating Plant","unit_number":"Unit 2","nrc_reactor_webpage":"http://www.nrc.gov/info-finder/reactor/vog2.html","docket_number":"05000425'","location":"Waynesboro, GA (26 MI SE of Augusta, GA)","nrc_region":"2","licensee":"Southern Nuclear Operating Co.","reactor_containment_type":"PWR-DRYAMB","steam_system_supplier_design":"WEST 4LP","architect_engineer":"SBEC","contructor":"GPC","construction_permit_issued":"1974-06-28T00:00:00.000Z","operating_license_issued":"1989-03-31T00:00:00.000Z","commercial_operation":"1989-05-20T00:00:00.000Z","renewed_operating_license_issued":"2009-06-03T00:00:00.000Z","operating_license_expires":"2049-02-09T00:00:00.000Z","licensed_mwt":"3625.6","notes":null,"capacity_factor_percent_2012":"1.02","capacity_factor_percent_2011":"0.94","capacity_factor_percent_2010":"0.93","capacity_factor_percent_2009":"1.01","capacity_factor_percent_2008":"0.88","capacity_factor_percent_2007":"0.83","serialid":97},{"plantname":"Waterford Steam Electric Station","unit_number":"Unit 3","nrc_reactor_webpage":"http://www.nrc.gov/info-finder/reactor/wat3.html","docket_number":"5000382","location":"Killona, LA (25 MI W of New Orleans, LA)","nrc_region":"4","licensee":"Entergy Operations, Inc.","reactor_containment_type":"PWR-DRYAMB","steam_system_supplier_design":"COMB CE","architect_engineer":"EBSO","contructor":"EBSO","construction_permit_issued":"1974-11-14T00:00:00.000Z","operating_license_issued":"1985-03-16T00:00:00.000Z","commercial_operation":"1985-09-24T00:00:00.000Z","renewed_operating_license_issued":null,"operating_license_expires":"2024-12-18T00:00:00.000Z","licensed_mwt":"3716","notes":null,"capacity_factor_percent_2012":"0.77","capacity_factor_percent_2011":"0.82","capacity_factor_percent_2010":"1","capacity_factor_percent_2009":"0.87","capacity_factor_percent_2008":"0.89","capacity_factor_percent_2007":"0.98","serialid":98},{"plantname":"Watts Bar Nuclear Plant","unit_number":"Unit 1","nrc_reactor_webpage":"http://www.nrc.gov/info-finder/reactor/wb1.html","docket_number":"5000390","location":"Spring City, TN (60 MI SW of Knoxville, TN)","nrc_region":"2","licensee":"Tenessee Valley Authority","reactor_containment_type":"PWR-ICECND","steam_system_supplier_design":"WEST 4LP","architect_engineer":"TVA","contructor":"TVA","construction_permit_issued":"1973-01-23T00:00:00.000Z","operating_license_issued":"1996-02-07T00:00:00.000Z","commercial_operation":"1996-05-27T00:00:00.000Z","renewed_operating_license_issued":null,"operating_license_expires":"2035-11-09T00:00:00.000Z","licensed_mwt":"3459","notes":null,"capacity_factor_percent_2012":"0.87","capacity_factor_percent_2011":"0.84","capacity_factor_percent_2010":"0.99","capacity_factor_percent_2009":"0.94","capacity_factor_percent_2008":"0.82","capacity_factor_percent_2007":"1.02","serialid":99},{"plantname":"Wolf Creek Generating Station","unit_number":"Unit 1","nrc_reactor_webpage":"http://www.nrc.gov/info-finder/reactor/wc.html","docket_number":"5000482","location":"Burlington (Coffey County), KS (28 MI SE of Emporia,_KS)","nrc_region":"4","licensee":"Wolf Creek Nuclear Operating Corp.","reactor_containment_type":"PWR-DRYAMB","steam_system_supplier_design":"WEST 4LP","architect_engineer":"BECH","contructor":"DANI","construction_permit_issued":"1977-05-17T00:00:00.000Z","operating_license_issued":"1985-06-04T00:00:00.000Z","commercial_operation":"1985-09-03T00:00:00.000Z","renewed_operating_license_issued":"2008-11-20T00:00:00.000Z","operating_license_expires":"2045-03-11T00:00:00.000Z","licensed_mwt":"3565","notes":"The original OL (NPF-32) was issued on March 11, 1985. This license was superseded by OL( NPF-42) issued on June 4, 1985.","capacity_factor_percent_2012":"0.8","capacity_factor_percent_2011":"0.72","capacity_factor_percent_2010":"0.86","capacity_factor_percent_2009":"0.86","capacity_factor_percent_2008":"0.83","capacity_factor_percent_2007":"1.02","serialid":100}]}